Workbook

Sheet Résumé
A1: Leads Asie du Sud-Est — Magasins de vinyles & revendeurs de cartes Pokémon
A2: Recherche web réalisée le 08/10/2026 — Thaïlande, Vietnam, Philippines, Singapour, Indonésie
A4: Pays | B4: Vinyles | C4: Vinyles statut « Actif » | D4: Vinyles avec ≥1 contact | E4: Pokémon | F4: Pokémon priorité A | G4: Pokémon priorité B | H4: Pokémon avec ≥1 contact
A5: Thaïlande | B5: =COUNTIF(Vinyles!$C:$C,$A5) -> 39 | C5: =COUNTIFS(Vinyles!$C:$C,$A5,Vinyles!$Q:$Q,"Actif") -> 19 | D5: =COUNTIFS(Vinyles!$C:$C,$A5,Vinyles!$R:$R,">0") -> 13 | E5: =COUNTIF(Pokémon!$C:$C,$A5) -> 45 | F5: =COUNTIFS(Pokémon!$C:$C,$A5,Pokémon!$I:$I,"A") -> 7 | G5: =COUNTIFS(Pokémon!$C:$C,$A5,Pokémon!$I:$I,"B") -> 6 | H5: =COUNTIFS(Pokémon!$C:$C,$A5,Pokémon!$U:$U,">0") -> 35
A6: Vietnam | B6: =COUNTIF(Vinyles!$C:$C,$A6) -> 32 | C6: =COUNTIFS(Vinyles!$C:$C,$A6,Vinyles!$Q:$Q,"Actif") -> 5 | D6: =COUNTIFS(Vinyles!$C:$C,$A6,Vinyles!$R:$R,">0") -> 26 | E6: =COUNTIF(Pokémon!$C:$C,$A6) -> 33 | F6: =COUNTIFS(Pokémon!$C:$C,$A6,Pokémon!$I:$I,"A") -> 4 | G6: =COUNTIFS(Pokémon!$C:$C,$A6,Pokémon!$I:$I,"B") -> 7 | H6: =COUNTIFS(Pokémon!$C:$C,$A6,Pokémon!$U:$U,">0") -> 20
A7: Philippines | B7: =COUNTIF(Vinyles!$C:$C,$A7) -> 53 | C7: =COUNTIFS(Vinyles!$C:$C,$A7,Vinyles!$Q:$Q,"Actif") -> 5 | D7: =COUNTIFS(Vinyles!$C:$C,$A7,Vinyles!$R:$R,">0") -> 28 | E7: =COUNTIF(Pokémon!$C:$C,$A7) -> 54 | F7: =COUNTIFS(Pokémon!$C:$C,$A7,Pokémon!$I:$I,"A") -> 8 | G7: =COUNTIFS(Pokémon!$C:$C,$A7,Pokémon!$I:$I,"B") -> 11 | H7: =COUNTIFS(Pokémon!$C:$C,$A7,Pokémon!$U:$U,">0") -> 25
A8: Singapour | B8: =COUNTIF(Vinyles!$C:$C,$A8) -> 35 | C8: =COUNTIFS(Vinyles!$C:$C,$A8,Vinyles!$Q:$Q,"Actif") -> 15 | D8: =COUNTIFS(Vinyles!$C:$C,$A8,Vinyles!$R:$R,">0") -> 17 | E8: =COUNTIF(Pokémon!$C:$C,$A8) -> 78 | F8: =COUNTIFS(Pokémon!$C:$C,$A8,Pokémon!$I:$I,"A") -> 7 | G8: =COUNTIFS(Pokémon!$C:$C,$A8,Pokémon!$I:$I,"B") -> 36 | H8: =COUNTIFS(Pokémon!$C:$C,$A8,Pokémon!$U:$U,">0") -> 52
A9: Indonésie | B9: =COUNTIF(Vinyles!$C:$C,$A9) -> 56 | C9: =COUNTIFS(Vinyles!$C:$C,$A9,Vinyles!$Q:$Q,"Actif") -> 11 | D9: =COUNTIFS(Vinyles!$C:$C,$A9,Vinyles!$R:$R,">0") -> 30 | E9: =COUNTIF(Pokémon!$C:$C,$A9) -> 61 | F9: =COUNTIFS(Pokémon!$C:$C,$A9,Pokémon!$I:$I,"A") -> 5 | G9: =COUNTIFS(Pokémon!$C:$C,$A9,Pokémon!$I:$I,"B") -> 22 | H9: =COUNTIFS(Pokémon!$C:$C,$A9,Pokémon!$U:$U,">0") -> 32
A10: Total | B10: =SUM(B5:B9) -> 215 | C10: =SUM(C5:C9) -> 55 | D10: =SUM(D5:D9) -> 114 | E10: =SUM(E5:E9) -> 271 | F10: =SUM(F5:F9) -> 31 | G10: =SUM(G5:G9) -> 82 | H10: =SUM(H5:H9) -> 164
A12: Comment lire le fichier
A13: • Onglet « Vinyles » : disquaires physiques, stands de marché, cafés/bars et boutiques hi-fi qui vendent des vinyles, vendeurs en ligne (site, Shopee/Lazada/Tokopedia, Instagram/Facebook, Discogs), labels/distributeurs.
A14: • Onglet « Pokémon » : boutiques TCG et revendeurs de cartes Pokémon, triés par pays puis par taille. « Gros items (preuves) » = ce qui a été vu dans les sources (booster boxes, cases, ETB, slabs PSA/BGS/CGC, vintage…).
A15: • Taille reseller : Gros = gros revendeur / distributeur / chaîne / grosse boutique en ligne ; Moyen = boutique dédiée vendant des boîtes scellées ; Petit = petit vendeur ; Inconnu = pas assez d'info.
A16: • Priorité (formule) : A = taille « Gros », ou gros items prouvés + vente en live ; B = taille « Moyen » ou gros items prouvés ; C = le reste.
A17: • Statut : Actif = activité vue en 2024-2026 ; Non vérifié = pas de preuve récente ; Peut-être fermé = une source évoque une fermeture (à vérifier avant contact).
A18: • Nb canaux de contact (formule) = nombre de champs remplis parmi Site web, Instagram, Facebook, TikTok, Téléphone, Email.
A19: • Google Maps : « Voir sur Maps » = lien trouvé dans les sources ; « Rechercher sur Maps » = lien de recherche généré à partir du nom et de l'adresse (boutiques physiques uniquement).
A20: Méthode et limites
A21: • Données collectées par recherche web (guides, annuaires, articles, forums, profils Instagram/Facebook/TikTok, boutiques Shopee/Lazada/Tokopedia/Carousell/Discogs), en anglais et en langues locales.
A22: • Chaque ligne cite au moins une source (colonne « Sources », la première est cliquable). Aucun contact n'a été inventé : un champ vide signifie que l'information n'a pas été trouvée.
A23: • Les petites boutiques changent vite (déménagements, fermetures, changement de compte Instagram) : vérifier le compte avant toute prise de contact.
A24: • Doublons fusionnés automatiquement (même nom, même Instagram, même page Facebook ou même site web dans un pays).

Sheet Vinyles
A1: # | B1: Nom | C1: Pays | D1: Ville | E1: Adresse / zone | F1: Type | G1: Spécialité | H1: Site web | I1: Instagram | J1: Facebook | K1: TikTok | L1: Téléphone / WhatsApp | M1: Email | N1: Marketplaces (Shopee, Lazada, Discogs…) | O1: Google Maps | P1: Vente en live | Q1: Statut | R1: Nb canaux de contact | S1: Notes | T1: Sources
A2: 1 | B2: 1979 Vinyl | C2: Thaïlande | D2: Bangkok | E2: 3rd floor, Fortune Town, 1 Ratchadaphisek Rd (MRT Rama 9) - per Asia City | F2: Boutique physique | G2: Secondhand oldies, rock, obscure 90s; Thorens turntables | J2: https://www.facebook.com/1979vinyl | O2: Rechercher sur Maps | Q2: Non vérifié | R2: =COUNTA(H2:M2) -> 1 | S2: Asia City listing; BK also gives Black Amber/Bungkumhouse address for 1979 Vinyls - may be related. | T2: https://bk.asia-city.com/shopping/article/best-shops-buy-vinyl-records-portable-turntables-bangkok-3
A3: 2 | B3: 242 Record Store | C3: Thaïlande | D3: Bangkok | E3: Room 242, 2nd floor, River City Bangkok, Charoen Krung 24, Bangkok | F3: Boutique physique | G3: Vinyl, CDs, tapes, posters, merch | I3: https://www.instagram.com/242recordsstore | O3: Rechercher sur Maps | Q3: Non vérifié | R3: =COUNTA(H3:M3) -> 1 | S3: ~3,200 IG followers; related label account @242records_bkk. | T3: https://www.instagram.com/242recordsstore/
A4: 3 | B4: Baa Records | C4: Thaïlande | D4: Bangkok | E4: Small storefront on Charoen Krung Rd (Entertainment Project), Bangkok; main base in Songkhla | F4: Boutique physique | G4: Vinyl records | O4: Rechercher sur Maps | Q4: Non vérifié | R4: =COUNTA(H4:M4) -> 0 | S4: Main base in Songkhla province with a Bangkok storefront per Time Out (Thai). | T4: https://www.timeout.com/bangkok/th/music/entertainment-project
A5: 4 | B5: Bungkumhouse Records | C5: Thaïlande | D5: Bangkok | E5: 4th floor, Black Amber Building, Sukhumvit Soi 55 (Thonglor, between Soi 5 and 7), Bangkok | F5: Boutique physique | G5: 80s-90s classics, Britpop, alt rock, soul, funk, electronica; local Thai indie releases | L5: 086-606-2230 | O5: Rechercher sur Maps | Q5: Actif | R5: =COUNTA(H5:M5) -> 1 | S5: Also spelled Burngkumhouse. Open Wed/Tue-Sun 1pm-9pm. BK Magazine lists 1979 Vinyls at the same Black Amber address/phone. | T5: https://www.timeout.com/bangkok/shopping/burngkumhouse-records | https://www.bkmagazine.com/arts-culture/where-to-find-bangkoks-best-record-stores-and-vinyl-bars/ | https://www.bkmagazine.com/nightlife/bangkok-bar-club/1979-cafe-and-unknown-pleasures/
A6: 5 | B6: CD Cosmos | C6: Thaïlande | D6: Bangkok | E6: Chatuchak, Bangkok | F6: Boutique physique | G6: Records and CDs | O6: Rechercher sur Maps | Q6: Non vérifié | R6: =COUNTA(H6:M6) -> 0 | S6: Listed in Time Out Bangkok (Thai) record shop guide. | T6: https://www.timeout.com/bangkok/th/music/cd-cosmos
A7: 6 | B7: Coconut Records | C7: Thaïlande | D7: Bangkok | E7: Room 3027, 3rd floor, Fortune Town, Ratchadaphisek Rd, Din Daeng, Bangkok | F7: Boutique physique | G7: Thai 90s releases, classic luk thung and molam; used vinyl | O7: Rechercher sur Maps | Q7: Non vérifié | R7: =COUNTA(H7:M7) -> 0 | S7: Open 11:30am-8pm daily; check Facebook for event closures. | T7: https://www.timeout.com/bangkok/music/coconut-records
A8: 7 | B8: DP Music | C8: Thaïlande | D8: Bangkok | E8: Building near MRT Rama 9, Bangkok | F8: Boutique physique | G8: Vinyl records | O8: Rechercher sur Maps | Q8: Non vérifié | R8: =COUNTA(H8:M8) -> 0 | S8: Listed in Time Out Bangkok (Thai) record shop guide. | T8: https://www.timeout.com/bangkok/th/music/dp-music
A9: 8 | B9: Fat Black Record | C9: Thaïlande | D9: Bangkok | E9: 345 Thara Rom Alley, Hua Mak, Bang Kapi, Bangkok | F9: Boutique physique | G9: New pressings plus some vintage; hi-fi gear and turntables (Crosley to Rega) | L9: 087-124-4421 | O9: Rechercher sur Maps | Q9: Actif | R9: =COUNTA(H9:M9) -> 1 | S9: Time Out Bangkok guide. Open daily noon-8pm. | T9: https://www.timeout.com/bangkok/shopping/fat-black-record | https://www.timeout.com/bangkok/music/best-record-shops-in-bangkok
A10: 9 | B10: Format BKK | C10: Thaïlande | D10: Bangkok | E10: Charoen Phon 1 Alley, Ari, Phaya Thai, Bangkok | F10: Boutique physique | G10: Offbeat Thai and international releases, 60s-90s secondhand; turntables (Gadhouse brand); sleeve-painting workshops | O10: Rechercher sur Maps | Q10: Actif | R10: =COUNTA(H10:M10) -> 0 | S10: Linked to Gadhouse turntable brand. Open daily 11am-8pm. New addition to Time Out 2026 guide. | T10: https://www.timeout.com/bangkok/music/best-record-shops-in-bangkok | https://www.timeout.com/bangkok/things-to-do/paint-vinyl-records-at-format-bkk
A11: 10 | B11: Garage Records | C11: Thaïlande | D11: Bangkok | E11: Lad Phrao Soi 8 (Yaek 9), Bangkok | F11: Boutique physique | G11: Rare finds, 80s-90s alternative rock | O11: Rechercher sur Maps | Q11: Non vérifié | R11: =COUNTA(H11:M11) -> 0 | S11: Listed by BK Magazine. Listed in BK Magazine roundup (date uncertain, 2019-2025). | T11: https://www.bkmagazine.com/arts-culture/where-to-find-bangkoks-best-record-stores-and-vinyl-bars/
A12: 11 | B12: Get Back and Jude Records | C12: Thaïlande | D12: Bangkok | E12: 399 Thanon Yaowaphanit, Samphanthawong (Yaowarat/Song Wat), Bangkok; pop-ups at Siam Discovery 2F and Siam Paragon 5F (Nextopia) | F12: Boutique physique | G12: Vinyl, esp. 7-inch singles and early pressings | O12: Rechercher sur Maps | Q12: Actif | R12: =COUNTA(H12:M12) -> 0 | S12: Time Out Bangkok 2026 guide. Open 11am-8pm daily. Has mall pop-up outposts. | T12: https://www.timeout.com/bangkok/music/get-back-and-jude-records | https://www.timeout.com/bangkok/music/best-record-shops-in-bangkok
A13: 12 | B13: Hall of Fame Records | C13: Thaïlande | D13: Bangkok | E13: 3rd floor (3058), Fortune Town, Ratchadaphisek Rd, Din Daeng, Bangkok | F13: Boutique physique | G13: Used & new vinyl; international and Thai hits; classic rock, country, European ambient; claims 40,000+ titles | O13: Rechercher sur Maps | Q13: Actif | R13: =COUNTA(H13:M13) -> 0 | S13: Once had several branches (incl. Thanya Shopping Park, Srinakarin); now one walk-in store at Fortune Town. Open 1pm-8pm daily. Possibly Bangkok's biggest record shop. | T13: https://www.timeout.com/bangkok/shopping/hall-of-fame-records | https://www.timeout.com/bangkok/music/best-record-shops-in-bangkok | https://citynomads.com/8-records-stores-in-bangkok-for-vinyl-music-cassettes-and-cds/
A14: 13 | B14: HAVE YOU HEARD? Records | C14: Thaïlande | D14: Bangkok | E14: Entertainment Project, 1107 Si Phraya Rd (Charoen Krung 43 area), Bang Rak, Bangkok | F14: Boutique physique | G14: Indie/alternative, soul, funk, hip-hop, house, techno; new vinyl | O14: Rechercher sur Maps | Q14: Actif | R14: =COUNTA(H14:M14) -> 0 | S14: Founded 2021 by indie promoters. Open Wed/Thu/Sun 12-8pm, Fri-Sat until midnight; closed Mon-Tue. | T14: https://www.timeout.com/bangkok/music/have-you-heard-records-entertainment-project | https://www.timeout.com/bangkok/music/best-record-shops-in-bangkok
A15: 14 | B15: More Rice Records | C15: Thaïlande | D15: Bangkok | E15: Sukhumvit Soi 31 / Phrom Phong back sois (near BTS Phrom Phong), Bangkok | F15: Boutique + en ligne | G15: House, techno, electronic; new second-hand stock every Thursday; label 'Made in Asia since 2016' | I15: https://www.instagram.com/morericerecords | O15: Rechercher sur Maps | Q15: Non vérifié | R15: =COUNTA(H15:M15) -> 1 | S15: Club-music label turned record store, store opened March 2021. Store IG @morerice.recordstore; hours Tue-Fri 1-8pm, Sat 3-8pm; new secondhand stock every Thursday. | T15: https://www.instagram.com/morericerecords/ | https://www.instagram.com/morerice.recordstore/ | https://www.bkmagazine.com/arts-culture/where-to-find-bangkoks-best-record-stores-and-vinyl-bars/ | https://thestandard.co/pop-cast-more-rice-record-store-playlist/
A16: 15 | B16: Nong Taprachan | C16: Thaïlande | D16: Bangkok | E16: 14 Tha Prachan (Wang Lang / Rot Fai Pier Alley area), Phra Borom Maha Ratchawang, Phra Nakhon, Bangkok | F16: Boutique physique | G16: New and classic Thai albums, Thai music past and present, some metal | O16: Rechercher sur Maps | Q16: Actif | R16: =COUNTA(H16:M16) -> 0 | S16: #1 in Time Out Bangkok record shop guide (Feb 2026). Open daily 11am-6:30pm; hosts young band sets. | T16: https://www.timeout.com/bangkok/music/nong-taprachan | https://www.timeout.com/bangkok/music/best-record-shops-in-bangkok
A17: 16 | B17: PPrecordsrecords | C17: Thaïlande | D17: Bangkok | F17: Vendeur réseaux sociaux | G17: Vinyl records; worldwide shipping; orders via DM | I17: https://www.instagram.com/pprecordsrecords | Q17: Non vérifié | R17: =COUNTA(H17:M17) -> 1 | S17: Online seller based in Bangkok. | T17: https://www.instagram.com/pprecordsrecords/
A18: 17 | B18: Record Record. | C18: Thaïlande | D18: Bangkok | E18: Pop-up at Foundry Creative Hub (per IG) | F18: Boutique + en ligne | G18: Vinyl records and turntables | I18: https://www.instagram.com/recordrecord.th | O18: Rechercher sur Maps | Q18: Non vérifié | R18: =COUNTA(H18:M18) -> 1 | S18: ~22K IG followers; pop-up open 12-8pm, closed Mondays. | T18: https://www.instagram.com/recordrecord.th/
A19: 18 | B19: Record Shop (Raan Pan Sieng) | C19: Thaïlande | D19: Bangkok | E19: 3 Soi Pradiphat 19, Pradiphat Rd, Samsen Nai, Phaya Thai, Bangkok | F19: Boutique physique | G19: Vintage and current albums, rare items; Thai cassettes and LPs | O19: Rechercher sur Maps | Q19: Actif | R19: =COUNTA(H19:M19) -> 0 | S19: Listed in Time Out Bangkok record shop guide. Open 10:30am-9pm. | T19: https://www.timeout.com/bangkok/shopping/record-shop-raan-pan-sieng | https://www.timeout.com/bangkok/music/best-record-shops-in-bangkok
A20: 19 | B20: Record This | C20: Thaïlande | D20: Bangkok | E20: 3rd floor, Central Ladprao, Bangkok | F20: Boutique + en ligne | G20: Vinyl records | I20: https://www.instagram.com/recordthis_vinyl | O20: Rechercher sur Maps | Q20: Non vérifié | R20: =COUNTA(H20:M20) -> 1 | S20: Bangkok-based; ~1,300 IG followers. | T20: https://www.instagram.com/recordthis_vinyl/
A21: 20 | B21: recordoffee (record & coffee) | C21: Thaïlande | D21: Bangkok | E21: Charoen Krung 29, Bangkok | F21: Café / bar avec boutique | G21: Records + coffee | I21: https://www.instagram.com/recordoffee | O21: Rechercher sur Maps | Q21: Non vérifié | R21: =COUNTA(H21:M21) -> 1 | S21: Weekdays 9:30-18:00, weekends 8:00-20:00, closed Tue. | T21: https://www.instagram.com/recordoffee/
A22: 21 | B22: Recoroom Vinyl & Vintage Audio | C22: Thaïlande | D22: Bangkok | E22: Building fronting Ekamai bus terminal (Ekkamai), Khlong Toei, Bangkok 10110 (older listings: Ekkamai 10 / Sukhumvit Soi 31 / Thetsaban Songkhro Rd, Chatuchak) | F22: Boutique physique | G22: Used/hand-picked vinyl: soul, funk, blues, rock; vintage audio equipment; listening turntable | O22: Rechercher sur Maps | Q22: Actif | R22: =COUNTA(H22:M22) -> 0 | S22: Time Out Bangkok 2026 guide; ranked #147 in The Vinyl Factory world's best record shops. Open daily ~11am-7pm. Address has moved several times - confirm. | T22: https://www.timeout.com/bangkok/music/recoroom-vinyl-and-vintage-audio | https://www.timeout.com/bangkok/music/best-record-shops-in-bangkok | https://thevinylfactory.com/features/the-worlds-best-record-shops-147-recoroom-vinyl-vintage-audio-bangkok
A23: 22 | B23: Sex Record Shop | C23: Thaïlande | D23: Bangkok | E23: 2nd floor, Seenspace, Thonglor Soi 13, Bangkok | F23: Boutique physique | G23: New & used LPs; 70s-80s heavy rock, 90s alternative, film soundtracks | L23: 02-185-2728 | O23: Rechercher sur Maps | Q23: Non vérifié | R23: =COUNTA(H23:M23) -> 1 | S23: Listed in BK Magazine 2019 roundup; no recent evidence seen. Listed in BK Magazine roundup (date uncertain, 2019-2025). | T23: https://www.bkmagazine.com/arts-culture/where-to-find-bangkoks-best-record-stores-and-vinyl-bars/ | https://bk.asia-city.com/shopping/article/best-shops-buy-vinyl-records-portable-turntables-bangkok
A24: 23 | B24: Tang Siang Thai | C24: Thaïlande | D24: Bangkok | E24: Charoenkrung Soi 11 (near MRT Sam Yot), Bangkok | F24: Boutique physique | G24: 60s-70s LPs, Thai and Chinese pressings; used | O24: Rechercher sur Maps | Q24: Non vérifié | R24: =COUNTA(H24:M24) -> 0 | S24: Old-school shop listed by BK Magazine. Listed in BK Magazine roundup (date uncertain, 2019-2025). | T24: https://www.bkmagazine.com/arts-culture/where-to-find-bangkoks-best-record-stores-and-vinyl-bars/
A25: 24 | B25: Tonchabab Record Shop | C25: Thaïlande | D25: Bangkok | E25: 10 Boonsiri Rd (Phra Nakhon) and Pattanakarn Rd branch, Bangkok | F25: Boutique physique | G25: Rare world music, luk thung, 60s-70s pop; used | O25: Rechercher sur Maps | Q25: Non vérifié | R25: =COUNTA(H25:M25) -> 0 | S25: Family-run, two branches, visits by appointment. Listed in BK Magazine roundup (date uncertain, 2019-2025). | T25: https://www.bkmagazine.com/arts-culture/where-to-find-bangkoks-best-record-stores-and-vinyl-bars/ | https://bk.asia-city.com/shopping/article/best-shops-buy-vinyl-records-portable-turntables-bangkok
A26: 25 | B26: Trackaddict Record | C26: Thaïlande | D26: Bangkok | E26: 47 MT&T Building, Soi Pridi Banomyong 3 (Sukhumvit 69 area), Watthana, Bangkok 10110 | F26: Boutique physique | G26: Used/rare vinyl from ~300 THB; rock, R&B, soul, soundtracks | O26: Rechercher sur Maps | Q26: Actif | R26: =COUNTA(H26:M26) -> 0 | S26: Also written Track Addict. Weekdays 9am-8pm, weekends noon-8pm. | T26: https://timeout.com/bangkok/shopping/trackaddict-record | https://citynomads.com/8-records-stores-in-bangkok-for-vinyl-music-cassettes-and-cds/
A27: 26 | B27: Vinyl & Toys | C27: Thaïlande | D27: Bangkok | E27: 19 Pradit Manutham Rd (near Bangkok Resort), Lat Phrao, Bangkok 10230 (Ramintra); second branch at Fortune Town, Ratchadaphisek Rd | F27: Boutique physique | G27: Large used stock leaning Japanese jazz and soul; toys; coffee | O27: Rechercher sur Maps | Q27: Actif | R27: =COUNTA(H27:M27) -> 0 | S27: Simon Grigg describes Fortune Town branch as two adjacent shops (full price + bargain). Ramintra main shop. | T27: https://www.timeout.com/bangkok/music/vinyl-toys | https://www.thebangkoknavigator.simongrigg.info/
A28: 27 | B28: Vinyl Die Hards | C28: Thaïlande | D28: Bangkok | E28: 162 Srinagarindra Rd (opposite Paradise Park, Srinakarin Soi 44), Prawet, Bangkok | F28: Boutique physique | G28: Used vinyl from ~100 THB; classics (jazz, rock, pop) | O28: Rechercher sur Maps | Q28: Non vérifié | R28: =COUNTA(H28:M28) -> 0 | S28: Run by child of PS Audio's owner (PS Audio closed). | T28: https://www.timeout.com/bangkok/shopping/vinyl-die-hards | https://citynomads.com/8-records-stores-in-bangkok-for-vinyl-music-cassettes-and-cds/
A29: 28 | B29: Vinyl Feeling | C29: Thaïlande | D29: Bangkok | E29: Warehouse 30, Charoenkrung Soi 30, Bang Rak, Bangkok; corner in Another Story, EmQuartier 4F | F29: Boutique physique | G29: Hip-hop, R&B, drum and bass vinyl | O29: Rechercher sur Maps | Q29: Non vérifié | R29: =COUNTA(H29:M29) -> 0 | S29: Listed in Asia City / BK roundups (c.2019-2021). | T29: https://bk.asia-city.com/shopping/article/best-shops-buy-vinyl-records-portable-turntables-bangkok | https://www.bkmagazine.com/city-living/shopping-article-best-shops-buy-vinyl-records-portable-turntables-bangkok/
A30: 29 | B30: Vinyllica Record Fortune Town | C30: Thaïlande | D30: Bangkok | E30: Fortune Town, Ratchadaphisek Rd, Bangkok | F30: Boutique physique | G30: Hard rock & heavy metal focus; Thai and international records | I30: https://www.instagram.com/vinyllica_record_fortunetown | O30: Rechercher sur Maps | Q30: Non vérifié | R30: =COUNTA(H30:M30) -> 1 | S30: Thai name ไวนิลลิกา ฟอร์จูนทาวน์. | T30: https://www.instagram.com/vinyllica_record_fortunetown/ | https://www.bkmagazine.com/arts-culture/where-to-find-bangkoks-best-record-stores-and-vinyl-bars/
A31: 30 | B31: Zubaidah Records | C31: Thaïlande | D31: Bangkok | E31: Between BTS Ekkamai and BTS Phra Khanong, Bangkok | F31: Boutique physique | G31: Vinyl records | O31: Rechercher sur Maps | Q31: Non vérifié | R31: =COUNTA(H31:M31) -> 0 | S31: Listed in Simon Grigg's Bangkok Navigator record shop guide (compiled c.2021). | T31: https://www.thebangkoknavigator.simongrigg.info/
A32: 31 | B32: Zudrangma Records | C32: Thaïlande | D32: Bangkok | E32: 7/1 Sukhumvit Soi 51, Khlong Tan Nuea, Watthana, Bangkok | F32: Boutique + en ligne | G32: Molam, luk thung, Thai funk, world music, disco; own label reissues; new & used | L32: +66 83 063 1335 | O32: Rechercher sur Maps | Q32: Actif | R32: =COUNTA(H32:M32) -> 1 | S32: Owned by DJ Maft Sai. Wed-Sun 12-8pm. Has web shop. 4.6 on Wanderlog (120+ reviews). | T32: https://wanderlog.com/place/details/1841365/zudrangma-records | https://www.timeout.com/bangkok/shopping/zudrangma-records | https://citynomads.com/8-records-stores-in-bangkok-for-vinyl-music-cassettes-and-cds/
A33: 32 | B33: Anglo Siam Record Shop | C33: Thaïlande | D33: Chiang Mai | E33: Loi Kroh Rd, Chiang Mai | F33: Boutique physique | G33: Imported rare grooves and scarce Thai pressings; drinks while browsing | O33: Rechercher sur Maps | Q33: Actif | R33: =COUNTA(H33:M33) -> 0 | S33: New shop opened by DJ outfit Anglo Siam (Time Out Chiang Mai opening listing, Jan 10 - after the c.2025 top-11 list). Opens from midday. | T33: https://www.timeout.com/chiang-mai/things-to-do/dig-into-rare-grooves-at-the-anglo-siam-record-shop-opening
A34: 33 | B34: Deaf Shop | C34: Thaïlande | D34: Chiang Mai | E34: Old town, Chiang Mai (near Nuii Bar, Pra Pok Klao Rd Soi 1) | F34: Café / bar avec boutique | G34: Vinyl listening bar and record store; large LP collection | O34: Rechercher sur Maps | Q34: Actif | R34: =COUNTA(H34:M34) -> 0 | S34: Opened May 2022 by Mum Pimolpud and Laurens Brouwer. Open Thu-Sat evenings and Sunday afternoons. | T34: https://mixmag.asia/read/chiang-mai-first-vinyl-listening-bar-deaf-shop-local | https://cnxmag.beehiiv.com/p/deaf-shop-is-a-vinyl-listening-gem | https://www.timeout.com/chiang-mai/music/chiang-mais-top-11-places-to-dig-for-vinyl
A35: 34 | B35: Franc Haus | C35: Thaïlande | D35: Chiang Mai | E35: Upstairs at Potto diner, Nimman, Chiang Mai | F35: Boutique physique | G35: New releases (largest new-release range in the city) | O35: Rechercher sur Maps | Q35: Actif | R35: =COUNTA(H35:M35) -> 0 | S35: Small record shop listed in Time Out Chiang Mai top 11 (c.2025). | T35: https://www.timeout.com/chiang-mai/music/chiang-mais-top-11-places-to-dig-for-vinyl
A36: 35 | B36: HiFi.Day at Back2nd.CNX | C36: Thaïlande | D36: Chiang Mai | E36: Basement under Think Park, Nimman, Chiang Mai | F36: Boutique physique | G36: Secondhand vinyl, thrift-style; 100 THB clearance LP box; hi-fi | O36: Rechercher sur Maps | Q36: Actif | R36: =COUNTA(H36:M36) -> 0 | S36: Listed in Time Out Chiang Mai top 11 (c.2025). | T36: https://www.timeout.com/chiang-mai/music/chiang-mais-top-11-places-to-dig-for-vinyl
A37: 36 | B37: Noomtaofire Record | C37: Thaïlande | D37: Chiang Mai | E37: 62/6 Charoen Prathet Rd, Chang Khlan, Mueang Chiang Mai, Chiang Mai 50100 (upstairs of Lonewanderer clothing store) | F37: Boutique physique | G37: New and secondhand vinyl, all genres; small cafe | O37: Rechercher sur Maps | Q37: Actif | R37: =COUNTA(H37:M37) -> 0 | S37: Near the Ping River. Open daily 2pm-7:30pm. | T37: https://www.timeout.com/chiang-mai/music/noomtaofire-record | https://www.timeout.com/chiang-mai/music/chiang-mais-top-11-places-to-dig-for-vinyl
A38: 37 | B38: Thirty Records | C38: Thaïlande | D38: Chiang Mai | E38: 40 Sanambin Kao 4 Alley, Suthep, Mueang Chiang Mai, Chiang Mai 50200 | F38: Boutique physique | G38: Japanese, Thai and Western vinyl; cassettes; hi-fi listening space; budget 3-LP boxes for 100 THB | O38: Rechercher sur Maps | Q38: Actif | R38: =COUNTA(H38:M38) -> 0 | S38: Run by Khun Munee, opened early 2023. Open 11am-6pm, closed Wednesdays. | T38: https://www.timeout.com/chiang-mai/music/thirty-records | https://www.timeout.com/chiang-mai/music/chiang-mais-top-11-places-to-dig-for-vinyl
A39: 38 | B39: Wua Lai Record Shop | C39: Thaïlande | D39: Chiang Mai | E39: 1, 6 Wua Lai Rd, Haiya, Mueang Chiang Mai, Chiang Mai 50100 | F39: Boutique physique | G39: Largest record shop in Chiang Mai; used vinyl incl. Thai rarities (floor boxes, white-label station copies); turntables and speakers | O39: Rechercher sur Maps | Q39: Actif | R39: =COUNTA(H39:M39) -> 0 | S39: Longest-running vinyl seller in town (10+ years). Open 11am-6pm. Listed in Time Out Chiang Mai top 11 (c.2025). | T39: https://www.timeout.com/chiang-mai/music/wua-lai-record-shop | https://www.timeout.com/chiang-mai/music/chiang-mais-top-11-places-to-dig-for-vinyl | https://www.timeout.com/chiang-mai/news/inside-chiang-mais-vinyl-revival-080125
A40: 39 | B40: Sabai Vinyl Pattaya | C40: Thaïlande | D40: Pattaya | E40: 2nd floor, MS2021 (near Eiffel Tower and robot statue), Pattaya | F40: Boutique physique | G40: Vinyl records; buys collections | I40: https://www.instagram.com/sabaivinyl | O40: Rechercher sur Maps | Q40: Non vérifié | R40: =COUNTA(H40:M40) -> 1 | S40: Bills itself as Pattaya's number one record store; open daily 11am-10pm. | T40: https://www.instagram.com/sabaivinyl/
A41: 40 | B41: AnhDuy Audio | C41: Vietnam | D41: Hanoi | E41: 72 Trần Nhân Tông, Hai Bà Trưng, Hà Nội | F41: Boutique + en ligne | G41: Hi-fi audio shop selling vinyl: Trịnh Công Sơn, Khánh Ly, Bằng Kiều and others; turntables | H41: https://anhduyaudio.com | L41: 024 3972 5014 | O41: Rechercher sur Maps | Q41: Non vérifié | R41: =COUNTA(H41:M41) -> 2 | S41: Yellow Pages lists Công ty TNHH Quốc Tế Anh Duy (turntables) at 235 Điện Biên Phủ, Q3, HCMC, tel (028) 22437005. This may be an HCMC branch. | T41: https://mytour.vn/vi/blog/bai-viet/danh-sach-5-dia-chi-mua-dia-than-chat-luong-va-gia-ca-phai-chang-tai-ha-noi.html | https://yellowpages.vn/pdetail/663822/mâm-đĩa-than.html
A42: 41 | B42: Giang Nhạc Xưa | C42: Vietnam | D42: Hanoi | E42: 33 Trịnh Công Sơn, Nhật Tân, Tây Hồ, Hà Nội | F42: Boutique physique | G42: Vinyl (classic Vietnamese songs, rock e.g. Pink Floyd, Eagles), record players, gramophones, audiophile gear | H42: https://giangnhacxua.com | L42: +84 972 113 223 | O42: Rechercher sur Maps | Q42: Non vérifié | R42: =COUNTA(H42:M42) -> 2 | S42: Culture Trip: long narrow shop in southern Hanoi by the Sét River. Other sources give 377 Trần Đại Nghĩa (Mixmag) / 337 Trần Đại Nghĩa (dientulinhanh.com) - possibly older/another location. | T42: https://theculturetrip.com/asia/vietnam/articles/best-record-stores-in-hanoi | https://mytour.vn/vi/blog/bai-viet/danh-sach-5-dia-chi-mua-dia-than-chat-luong-va-gia-ca-phai-chang-tai-ha-noi.html | https://tripi.vn/blog/vi/xep-hang/top-5-diem-ban-dia-than-chat-luong-nhat-ha-noi-gia-ca-phai-chang-da-dang-mau-ma-tripi | https://dientulinhanh.com/dia-chi-mua-ban-dia-than-gia-re-chinh-hang-tai-ha-noi
A43: 42 | B43: Hoàng Gia Audio | C43: Vietnam | D43: Hanoi | F43: Boutique + en ligne | G43: Vinyl records and antique/vintage record players | H43: https://hoanggiaaudio.vn | L43: +84 975 884 009 | O43: Rechercher sur Maps | Q43: Non vérifié | R43: =COUNTA(H43:M43) -> 2 | T43: https://hoanggiaaudio.vn/news/dia-chi-ban-dia-than-chinh-hang-o-ha-noi-a332.html
A44: 43 | B44: Hà Nội Đĩa Than (Hanoi Vinyl Records) | C44: Vietnam | D44: Hanoi | F44: Boutique physique | G44: Vinyl records | O44: Rechercher sur Maps | Q44: Non vérifié | R44: =COUNTA(H44:M44) -> 0 | S44: Set up in 2010; long-time meeting spot for Hanoi vinyl fans (Vietcetera 2021). Founded by the father and uncle of a Vọc Records co-founder. | T44: https://vietcetera.com/en/reintroducing-the-vinyl-culture-to-vietnams-new-generation
A45: 44 | B45: LP Club | C45: Vietnam | D45: Hanoi | E45: 174 Kim Mã, Kim Mã ward, Ba Đình, Hà Nội | F45: Boutique physique | G45: Used + new vinyl, CDs; 2,000+ second-hand records; strong jazz section, rarities and new releases; also music production/distribution | H45: https://lpclub.vn | I45: https://www.instagram.com/lpclubhn | L45: +84 90 454 6883 | O45: Rechercher sur Maps | Q45: Non vérifié | R45: =COUNTA(H45:M45) -> 3 | S45: Opened 2018 by vinyl enthusiasts. Culture Trip lists it jointly with Vinyl4u (shared space); location description differs between sources. Shares venue with Montauk café/cocktail bar. Instagram: open daily 10:00-20:00. | T45: https://silverkris.singaporeair.com/guide/vietnam/han/shop-hanoi/lp-club/ | https://theculturetrip.com/asia/vietnam/articles/best-record-stores-in-hanoi | https://hivelife.com/vinyl-stores-vietnam/ | https://www.instagram.com/lpclubhn/ | https://www.saigoneer.com/hanoi-street-food-restaurants/26571-ngõ-nooks-hanoi-lp-club-vinyl-montauk-cocktail-bar-coffee-shop-review
A46: 45 | B46: RUA Vinyl Records | C46: Vietnam | D46: Hanoi | F46: Distributeur / grossiste | G46: Wholesale and retail of new and used records in 33, 45 and 78 rpm | J46: https://www.facebook.com/ruavinyl | Q46: Non vérifié | R46: =COUNTA(H46:M46) -> 1 | T46: https://www.facebook.com/ruavinyl/
A47: 46 | B47: Thảo Nhạc Xưa | C47: Vietnam | D47: Hanoi | E47: 58 Xã Đàn, Đống Đa, Hà Nội | F47: Boutique physique | G47: Vinyl, reel-to-reel tapes, cassettes, CDs; old music | J47: https://www.facebook.com/p/TH%E1%BA%A2O-NH%E1%BA%A0C-X%C6%AFA-100063630708271 | L47: +84 98 855 65 54 | O47: Rechercher sur Maps | Q47: Non vérifié | R47: =COUNTA(H47:M47) -> 2 | T47: https://www.facebook.com/p/TH%E1%BA%A2O-NH%E1%BA%A0C-X%C6%AFA-100063630708271/
A48: 47 | B48: Totem Vinyl - Tiệm Đĩa Than | C48: Vietnam | D48: Hanoi | E48: 2G Hoàng Hoa Thám, Thụy Khuê, Tây Hồ, Hà Nội | F48: Boutique physique | G48: High-grade used vinyl; funk/soul, electronic, jazz, jazz fusion, hip-hop; ~1,000 records; merch, slipmats, cleaning kits | I48: https://www.instagram.com/totem.vinyl | J48: https://www.facebook.com/totem.vinyl | L48: +84 585 732 251 | O48: Rechercher sur Maps | Q48: Actif | R48: =COUNTA(H48:M48) -> 3 | S48: Co-owner 'Red'. Open 13:00-19:00, closed Mondays (Instagram). ~2,100 IG followers. Listed in 2024 (Travel Weekly) and 2025 (Tripi) guides. | T48: https://www.facebook.com/totem.vinyl/ | https://www.travelweekly.com.au/article/vietnamese-vinyl-vendors-that-any-music-aficionado-needs-to-visit/ | https://theculturetrip.com/asia/vietnam/articles/best-record-stores-in-hanoi | https://www.instagram.com/totem.vinyl/ | https://tripi.vn/blog/vi/xep-hang/top-5-diem-ban-dia-than-chat-luong-nhat-ha-noi-gia-ca-phai-chang-da-dang-mau-ma-tripi
A49: 48 | B49: Vinyl4u | C49: Vietnam | D49: Hanoi | F49: Boutique physique | G49: Used vinyl; European and Japanese pressings of jazz, blues and classic rock in near-mint condition | O49: Rechercher sur Maps | Q49: Non vérifié | R49: =COUNTA(H49:M49) -> 0 | S49: Shares a room with LP Club according to Culture Trip. | T49: https://theculturetrip.com/asia/vietnam/articles/best-record-stores-in-hanoi
A50: 49 | B50: Vọc Records (VOC Records) | C50: Vietnam | D50: Hanoi | E50: Số 5, ngõ 198 Thái Hà, Đống Đa, Hà Nội | F50: Boutique physique | G50: Genuine new vinyl; special orders; vinyl label; organiser of Hanoi Records Day | Hi-fi audio dealer selling new vinyl LPs (incl. Vietnamese releases e.g. 'Nhiên') | H50: https://thienhaaudio.vn | L50: +84 983 83 46 46 | O50: Rechercher sur Maps | Q50: Non vérifié | R50: =COUNTA(H50:M50) -> 2 | S50: Founded by four friends; listening counter with turntables. Address/phone shared with Thiên Hà Audio (thienhaaudio.vn). Takes custom orders, home delivery. | Same address/phone as Vọc Records listing; may be the same operator. Mytour lists Vọc Records at this address and phone with this website; the two may share premises or Mytour may have mixed them up. | T50: https://vietcetera.com/en/reintroducing-the-vinyl-culture-to-vietnams-new-generation | https://saigoneer.com/saigon-music-art/24963-crate-digging-for-audio-gold-at-the-second-hanoi-records-day | https://mytour.vn/vi/blog/bai-viet/danh-sach-5-dia-chi-mua-dia-than-chat-luong-va-gia-ca-phai-chang-tai-ha-noi.html | https://thienhaaudio.vn/san-pham/dia-lp-nhien/
A51: 50 | B51: Điện tử Linh Anh | C51: Vietnam | D51: Hanoi | E51: 99 Hồ Ba Mẫu (Ô Đồng Lầm), Đống Đa, Hà Nội; 117 Phạm Văn Đồng, Mai Dịch, Cầu Giấy, Hà Nội; HCMC branches: 559 Phan Văn Trị, 129 Bình Thới, 151 Nguyễn Duy Dương | F51: Chaîne / grande enseigne | G51: Electronics/audio chain selling new sealed vinyl, CDs, USB music plus turntables, speakers, headphones | H51: https://dientulinhanh.com | L51: 1800 0035 | +84 989 142 688 | +84 946 142 688 | O51: Rechercher sur Maps | Q51: Non vérifié | R51: =COUNTA(H51:M51) -> 2 | S51: Has dedicated 'Đĩa than - Đĩa CD - USB' category; free delivery/installation in Hanoi & HCMC. Open 8:30-21:00. | T51: https://dientulinhanh.com/dia-chi-mua-ban-dia-than-gia-re-chinh-hang-tai-ha-noi | https://dientulinhanh.com/dia-than-dia-cd-usb | https://mytour.vn/vi/blog/bai-viet/danh-sach-5-dia-chi-mua-dia-than-chat-luong-va-gia-ca-phai-chang-tai-ha-noi.html
A52: 51 | B52: Đĩa Than - Haytch Vintage Sound | C52: Vietnam | D52: Hanoi | F52: Boutique physique | G52: Vinyl and tapes, vintage sound | J52: https://www.facebook.com/diathanhanoi | O52: Rechercher sur Maps | Q52: Non vérifié | R52: =COUNTA(H52:M52) -> 1 | S52: ~822 likes, ~2,542 check-ins on Facebook. Facebook check-ins suggest a physical location, but no address was found. Handle 'diathanhanoi'; not confirmed whether it is linked to Hà Nội Đĩa Than (est. 2010). | T52: https://www.facebook.com/diathanhanoi/
A53: 52 | B53: Đĩa Than Vintage (Hanoi Vintage Vinyl Shop) | C53: Vietnam | D53: Hanoi | E53: 147 Yên Phụ, Tây Hồ, Hà Nội | F53: Boutique + en ligne | G53: Used vinyl only, 5,000+ albums: pop rock, ballad, jazz, hip hop, electronic, country, easy listening, Japanese jazz; rare records for DJs/beatmakers; Blue Note; 1970s first pressings | I53: https://www.instagram.com/diathan.vintage | J53: https://www.facebook.com/diathanvintage | L53: +84 38 411 1175 | O53: Rechercher sur Maps | Q53: Actif | R53: =COUNTA(H53:M53) -> 3 | S53: Founded by Hanoi DJ 2T. Open Tue-Sun 9:30-19:00. Offers delivery. Separate online stock account @diathan.vintage.stock on Instagram. | T53: https://www.facebook.com/diathanvintage/ | https://www.trvlogue.com/en/hanoi-vintage-shops-west-lake | https://hivelife.com/vinyl-stores-vietnam/ | https://www.instagram.com/diathan.vintage/ | https://mytour.vn/vi/blog/bai-viet/danh-sach-5-dia-chi-mua-dia-than-chat-luong-va-gia-ca-phai-chang-tai-ha-noi.html
A54: 53 | B54: Analog Audio | C54: Vietnam | D54: Ho Chi Minh City | E54: 351/12A Lê Văn Sỹ, Phường 13, Quận 3, TP.HCM | F54: Boutique + en ligne | G54: New vinyl; 80s-90s albums, instrumental classics, international & Vietnamese; audiophile labels (STS Digital, Harmonix, Impex) | H54: https://analogaudio.vn | O54: Rechercher sur Maps | Q54: Non vérifié | R54: =COUNTA(H54:M54) -> 1 | S54: Forum users recommend 'Analog Lê Văn Sỹ' (2021). | T54: https://hivelife.com/vinyl-stores-vietnam/ | https://vnav.vn/threads/s%C3%A0i-g%C3%B2n-mua-%C4%91%C4%A9a-than-%E1%BB%9F-%C4%91%C3%A2u.117891/
A55: 54 | B55: Audio Space | C55: Vietnam | D55: Ho Chi Minh City | F55: Distributeur / grossiste | G55: Distributor that has released many Vietnamese vinyl albums | Q55: Non vérifié | R55: =COUNTA(H55:M55) -> 0 | S55: Vietnam News calls it a leading HCMC distributor of Vietnamese vinyl albums. Unclear whether it sells retail. | T55: https://vietnamnews.vn/life-style/518863/vinyl-records-make-a-comeback-with-new-albums.html
A56: 55 | B56: Bluish Records | C56: Vietnam | D56: Ho Chi Minh City | E56: 158/10 Nguyễn Công Trứ, Quận 1, TP.HCM (Biker Shield Bistro; from a 2024 event listing) | F56: Boutique physique | G56: Vinyl records; hosts vinyl record day events | O56: Rechercher sur Maps | Q56: Actif | R56: =COUNTA(H56:M56) -> 0 | S56: Vinyl Record Day event 6-7 July 2024 at Biker Shield Bistro, 158/10 Nguyễn Công Trứ, Q1. Address comes from the event venue; check that the shop is based there. | T56: https://saigoneer.com/saigon-events/27157-vinyl-record-day-bluish-records
A57: 56 | B57: CD – Bản ghi (Vinyl) Trường Chinh | C57: Vietnam | D57: Ho Chi Minh City | E57: 180 Trường Chinh, Tân Bình, TP.HCM | F57: Boutique physique | G57: CDs and vinyl records | L57: +84 909 375 959 | O57: Rechercher sur Maps | Q57: Non vérifié | R57: =COUNTA(H57:M57) -> 1 | S57: Name as given in the HCMtoplist listing; the trading name is unclear. | T57: https://www.hcmtoplist.com/top-20-dia-chi-ban-dia-cd-goc-tai-tphcm-gia-re-va-chat-luong
A58: 57 | B58: Có Gì Bán Đó Sài Gòn | C58: Vietnam | D58: Ho Chi Minh City | E58: 48 Trần Quang Diệu, Phường 14, Quận 3, TP.HCM | F58: Boutique physique | G58: US turntables (Crosley, Victrola) plus domestic and international vinyl | L58: +84 937 809 193 | O58: Rechercher sur Maps | Q58: Non vérifié | R58: =COUNTA(H58:M58) -> 1 | T58: https://www.hcmtoplist.com/top-5-dia-chi-ban-dia-than-o-sai-gon-uy-tin-chat-luong
A59: 58 | B59: Cửa Hàng Đĩa Than LP Vinyl | C59: Vietnam | D59: Ho Chi Minh City | E59: 313/56 Tỉnh lộ 10, An Lạc A, Bình Tân, TP.HCM | F59: Boutique physique | G59: Vinyl LPs, CDs, cassettes, tapes, accessories | J59: https://www.facebook.com/cuahangbandiathanlpvinyl | O59: Rechercher sur Maps | Q59: Non vérifié | R59: =COUNTA(H59:M59) -> 1 | T59: https://www.facebook.com/cuahangbandiathanlpvinyl/
A60: 59 | B60: Damn Shop | C60: Vietnam | D60: Ho Chi Minh City | F60: Boutique physique | G60: Skate/streetwear shop with small vinyl section; 90s rap and hip-hop 7-inches | O60: Rechercher sur Maps | Q60: Non vérifié | R60: =COUNTA(H60:M60) -> 0 | T60: https://www.travelweekly.com.au/article/vietnamese-vinyl-vendors-that-any-music-aficionado-needs-to-visit/
A61: 60 | B61: Hãng Đĩa Thời Đại (Times Records) | C61: Vietnam | D61: Ho Chi Minh City | E61: 6 Nguyễn Văn Nguyễn, Tân Định, Quận 1, TP.HCM | F61: Boutique + en ligne | G61: Indie label + shop; new vinyl, CDs, cassettes; Vietnamese releases plus imported pop, rock, alternative, jazz, oldies | H61: https://store.hangdiathoidai.com | J61: https://www.facebook.com/hangdiathoidai | L61: +84 90 308 80 38 | O61: Rechercher sur Maps | Q61: Non vérifié | R61: =COUNTA(H61:M61) -> 3 | S61: Independent label founded 2017 preserving analog music. An older forum comment says repeated calls went unanswered, so check before visiting. hangdiathoidai.com presents it as a label. | T61: https://hivelife.com/vinyl-stores-vietnam/ | https://www.facebook.com/hangdiathoidai/ | https://www.hcmtoplist.com/top-5-dia-chi-ban-dia-than-o-sai-gon-uy-tin-chat-luong | https://vnav.vn/threads/s%C3%A0i-g%C3%B2n-mua-%C4%91%C4%A9a-than-%E1%BB%9F-%C4%91%C3%A2u.117891/ | https://www.hangdiathoidai.com/about
A62: 61 | B62: Nhật Duy (băng đĩa gốc) | C62: Vietnam | D62: Ho Chi Minh City | E62: 18/75/1 Trần Quang Diệu, Quận 3, TP.HCM | F62: Boutique physique | G62: Original CDs, DVDs and vinyl; packaging and nationwide distribution | L62: +84 378 899 877 | O62: Rechercher sur Maps | Q62: Non vérifié | R62: =COUNTA(H62:M62) -> 1 | S62: Also offers packaging and nationwide distribution of discs. | T62: https://www.hcmtoplist.com/top-5-dia-chi-ban-dia-than-o-sai-gon-uy-tin-chat-luong
A63: 62 | B63: Saigon Vinyl Records | C63: Vietnam | D63: Ho Chi Minh City | F63: En ligne (site web) | G63: Imported international vinyl, mint-condition LPs | H63: https://saigonvinylrecords.com | I63: https://www.instagram.com/saigon_vinyl_records | J63: https://www.facebook.com/saigonvinylrecords | Q63: Non vérifié | R63: =COUNTA(H63:M63) -> 3 | T63: https://hivelife.com/vinyl-stores-vietnam/ | https://www.facebook.com/saigonvinylrecords/ | https://www.instagram.com/saigon_vinyl_records/
A64: 63 | B64: Sturmfrei Records | C64: Vietnam | D64: Ho Chi Minh City | F64: Vendeur réseaux sociaux | G64: Vinyl records | Q64: Non vérifié | R64: =COUNTA(H64:M64) -> 0 | S64: Listed with Bluish Records and District M on a Saigoneer vinyl record day event page. No other details found. | T64: https://saigoneer.com/saigon-events/27157-vinyl-record-day-bluish-records
A65: 64 | B65: Tiệm Sài Gòn Đĩa Than | C65: Vietnam | D65: Ho Chi Minh City | E65: 226B Nguyễn Văn Đậu, Phường 11, Bình Thạnh, TP.HCM | F65: Café / bar avec boutique | G65: Vinyl, turntables and turntable accessories | J65: https://www.facebook.com/cafesaigondiathan | L65: +84 93 804 59 11 | O65: Rechercher sur Maps | Q65: Non vérifié | R65: =COUNTA(H65:M65) -> 2 | S65: Forum users mention a café on Nguyễn Văn Đậu selling records (likely same). | T65: https://www.facebook.com/cafesaigondiathan/ | https://vnav.vn/threads/s%C3%A0i-g%C3%B2n-mua-%C4%91%C4%A9a-than-%E1%BB%9F-%C4%91%C3%A2u.117891/
A66: 65 | B66: Vina Groove | C66: Vietnam | D66: Ho Chi Minh City | E66: Pasteur Street, Quận 1, TP.HCM (shares space with Ronin Izakaya) | F66: Boutique + en ligne | G66: Used vinyl, 2,000+ records; funk, rock, jazz, fusion, hip hop, reggae, Japanese music | H66: https://vinagroove.com | I66: https://www.instagram.com/vinagroove.records | J66: https://www.facebook.com/vinagroove.records | O66: Rechercher sur Maps | Q66: Actif | R66: =COUNTA(H66:M66) -> 3 | S66: Run by Francois, long-term French resident. Open 13:00-20:00, closed Mondays. Earlier location had beer garden. Instagram (later): open ~16:00-21:00, closed Thu & Fri; no online sales, in-store digging only. Featured in a Travel Weekly guide from about early 2024. | T66: https://www.facebook.com/vinagroove.records/ | https://www.travelweekly.com.au/article/vietnamese-vinyl-vendors-that-any-music-aficionado-needs-to-visit/ | https://www.instagram.com/vinagroove.records/
A67: 66 | B67: Vinyl Sài Gòn | C67: Vietnam | D67: Ho Chi Minh City | E67: 6B Đinh Bộ Lĩnh, Bình Thạnh, TP.HCM | F67: Boutique + en ligne | G67: Vinyl records plus turntables, hi-fi/analog/studio audio equipment, speakers, cables | H67: https://vinylsaigon.vn | I67: https://www.instagram.com/vinylsaigon | J67: https://www.facebook.com/VinylSaiGon | L67: +84 937 738 343 | +84 977 043 608 | 028 3535 5377 | O67: Rechercher sur Maps | Q67: Actif | R67: =COUNTA(H67:M67) -> 4 | S67: Open Mon-Sat 8:30-20:00, Sun 8:30-19:00; same-day delivery in HCMC. Live website with a vinyl category (vinylsaigon.vn/products/category/dia-than). | T67: https://www.facebook.com/VinylSaiGon/ | https://www.instagram.com/vinylsaigon/ | https://vinylsaigon.vn/products/category/dia-than | https://www.hcmtoplist.com/top-5-dia-chi-ban-dia-than-o-sai-gon-uy-tin-chat-luong
A68: 67 | B68: Vinyl Việt | C68: Vietnam | D68: Ho Chi Minh City | E68: 112 Bắc Hải, Phường 6, Tân Bình, TP.HCM | F68: Boutique + en ligne | G68: Brand-new sealed vinyl | H68: https://vinyl.vn | I68: https://www.instagram.com/vinylviet | J68: https://www.facebook.com/vinylviet | O68: Rechercher sur Maps | Q68: Non vérifié | R68: =COUNTA(H68:M68) -> 3 | S68: Instagram bio: open daily 9:00-20:00. | T68: https://www.facebook.com/vinylviet/ | https://www.instagram.com/vinylviet/
A69: 68 | B69: Vũ Dương (CD - VCD - đĩa than) | C69: Vietnam | D69: Ho Chi Minh City | E69: 186 F-E-D Phan Văn Trị, Bình Thạnh, TP.HCM | F69: Boutique physique | G69: Cheap CDs, VCDs and vinyl for older players | L69: 028 6297 5209 | O69: Rechercher sur Maps | Q69: Non vérifié | R69: =COUNTA(H69:M69) -> 1 | S69: Mainly CDs/VCDs. The vinyl range is unclear, so check its size. | T69: https://www.hcmtoplist.com/top-20-dia-chi-ban-dia-cd-goc-tai-tphcm-gia-re-va-chat-luong
A70: 69 | B70: Đĩa Than 51 Sài Gòn | C70: Vietnam | D70: Ho Chi Minh City | E70: 148 Nguyễn Hậu, Tân Phú, TP.HCM | F70: Café / bar avec boutique | G70: New and used vinyl (Vietnamese & international), CDs, cassettes; folk, world, country; vinyl listening café | H70: https://vinylrecord51.com | J70: https://www.facebook.com/DiaThan51SaiGon | L70: +84 97 926 18 37 | +84 949 734 584 | O70: Rechercher sur Maps | Q70: Non vérifié | R70: =COUNTA(H70:M70) -> 3 | T70: https://www.facebook.com/DiaThan51SaiGon/ | https://vinylrecord51.com/ | https://www.hotdeal.vn/ho-chi-minh/cafe-vn/ca-phe-dia-than-51-sai-gon-noi-ky-uc-tim-ve-369556.html
A71: 70 | B71: Đĩa Than Mua Ở Đây | C71: Vietnam | D71: Ho Chi Minh City | E71: 148 Nguyễn Hậu, Tân Phú, TP.HCM | F71: Boutique + en ligne | G71: Vietnamese music, jazz, pop, rock vinyl incl. original historical pressings | H71: https://diathanmuaoday.com | L71: +84 902 984 264 | O71: Rechercher sur Maps | Q71: Non vérifié | R71: =COUNTA(H71:M71) -> 2 | S71: Same street address as Đĩa Than 51 Sài Gòn; possibly related. | T71: https://www.hcmtoplist.com/top-5-dia-chi-ban-dia-than-o-sai-gon-uy-tin-chat-luong
A72: 71 | B72: Audio.vn | C72: Vietnam | D72: Nationwide (online) | F72: En ligne (site web) | G72: Audio retailer with a dedicated vinyl (đĩa than) and original CD category | H72: https://audio.vn/product-category/danh-muc-san-pham/dia-than | Q72: Non vérifié | R72: =COUNTA(H72:M72) -> 1 | S72: Category title targets Hanoi, Saigon, Hai Phong and Da Nang buyers; ships nationwide. | T72: https://audio.vn/product-category/danh-muc-san-pham/dia-than
A73: 72 | B73: Manila Record Club (Discogs seller) | C73: Philippines | F73: Vendeur marketplace | G73: Vinyl incl. many 7-inch/45 RPM singles | N73: Discogs: https://www.discogs.com/seller/manilarecordclub/profile | Q73: Non vérifié | R73: =COUNTA(H73:M73) -> 0 | S73: Discogs seller located in the Philippines; 99.3% rating from 141 ratings. | T73: https://www.discogs.com/seller/manilarecordclub/profile?format=Vinyl
A74: 73 | B74: Plakada | C74: Philippines | F74: Vendeur réseaux sociaux | G74: Sealed vinyl albums, record players, complete audio setups | I74: https://www.instagram.com/plakadaph | Q74: Non vérifié | R74: =COUNTA(H74:M74) -> 1 | S74: Orders via Instagram DM. | T74: https://www.instagram.com/plakadaph/
A75: 74 | B75: vivalahvinyls (Discogs seller) | C75: Philippines | F75: Vendeur marketplace | G75: Vinyl records | N75: Discogs: https://www.discogs.com/seller/vivalahvinyls/profile | Q75: Non vérifié | R75: =COUNTA(H75:M75) -> 0 | S75: Discogs seller shipping from the Philippines; 100% rating from 94 ratings. | T75: https://www.discogs.com/seller/vivalahvinyls/profile
A76: 75 | B76: Sunny Day Records | C76: Philippines | D76: Bacolod | F76: Boutique physique | G76: Vinyl records | I76: https://www.instagram.com/sunnydayrecords | O76: Rechercher sur Maps | Q76: Non vérifié | R76: =COUNTA(H76:M76) -> 1 | S76: Independent record store in Bacolod City. | T76: https://www.instagram.com/sunnydayrecords/
A77: 76 | B77: Frankie Records | C77: Philippines | D77: Baguio | E77: Goshenland Towers, Upper Gen. Luna Rd., Baguio City | F77: Boutique physique | G77: Records, CDs and tapes | I77: https://www.instagram.com/hellofrankierecords | O77: Rechercher sur Maps | Q77: Non vérifié | R77: =COUNTA(H77:M77) -> 1 | S77: Mon-Sat 11:30AM-5PM; linked account @tokyo_musicclub (ships CDs nationwide). | T77: https://www.instagram.com/hellofrankierecords/ | https://www.instagram.com/tokyo_musicclub/
A78: 77 | B78: Plakafé | C78: Philippines | D78: Baguio | F78: Café / bar avec boutique | G78: Vinyl records in a café serving Filipino comfort food; live music on weekends | O78: Rechercher sur Maps | Q78: Non vérifié | R78: =COUNTA(H78:M78) -> 0 | S78: Named by The Vinyl City FB page as its Baguio outlet. | T78: https://wanderlog.com/place/details/1483770/plakafé | https://www.facebook.com/TheVinylCity/
A79: 78 | B79: The Vinyl City | C79: Philippines | D79: Baguio / Cagayan de Oro | F79: Vendeur réseaux sociaux | G79: Vinyl records | J79: https://www.facebook.com/TheVinylCity | Q79: Non vérifié | R79: =COUNTA(H79:M79) -> 1 | S79: FB listing points to outlets in Baguio and Cagayan de Oro. FB page directs buyers to Plakafé (Baguio) and Megadisc Play (Cagayan de Oro) or to an online list. | T79: https://www.facebook.com/TheVinylCity/
A80: 79 | B80: Megadisc Play | C80: Philippines | D80: Cagayan de Oro | F80: Boutique physique | G80: Vinyl records (outlet for The Vinyl City stock) | O80: Rechercher sur Maps | Q80: Non vérifié | R80: =COUNTA(H80:M80) -> 0 | S80: Named by The Vinyl City FB page as its Cagayan de Oro outlet; no other details found. | T80: https://www.facebook.com/TheVinylCity/
A81: 80 | B81: Little Rituals Records Cebu | C81: Philippines | D81: Cebu City | E81: 2F The Maze, Ayala Center Cebu, Cebu City | F81: Boutique physique | G81: Vinyl incl. OPM; lifestyle brand (est. 2016) | J81: https://www.facebook.com/littleritualscebu | L81: +63 927 208 0806 | O81: Rechercher sur Maps | Q81: Non vérifié | R81: =COUNTA(H81:M81) -> 2 | S81: Joined vinyl session/bazaar at Ayala Activity Center. | T81: https://nivessa.com/record-stores/philippines/central-visayas/cebu-city | https://www.facebook.com/littleritualscebu/ | https://www.facebook.com/PavementRecordsCebu/videos/opm-vinyl-records-available-at-ayala-center-cebu-maze-zone-little-rituals-/2060756574180873/
A82: 81 | B82: Melt Records | C82: Philippines | D82: Cebu City | F82: Distributeur / grossiste | G82: Indie label releasing limited colored vinyl (e.g., with Transfer of Power Records) | J82: https://www.facebook.com/meltrecordsph | Q82: Non vérifié | R82: =COUNTA(H82:M82) -> 1 | S82: Independent record label in Cebu City selling own vinyl releases. | T82: https://www.facebook.com/meltrecordsph/
A83: 82 | B83: Pavement Records Cebu | C83: Philippines | D83: Cebu City | E83: 2F J-Block Building, Apitong St., Cebu City (landmark: Red House Taiwan) | F83: Café / bar avec boutique | G83: Vinyl, turntables and analog gear; listening bar with themed vinyl nights | I83: https://www.instagram.com/pavementrecordscebu | J83: https://www.facebook.com/PavementRecordsCebu | L83: 0968 856 9726 | O83: Rechercher sur Maps | Q83: Non vérifié | R83: =COUNTA(H83:M83) -> 3 | S83: Since 2015; Mon-Sat 5PM-2AM. | T83: https://www.instagram.com/pavementrecordscebu/ | https://www.facebook.com/PavementRecordsCebu/
A84: 83 | B84: Quiet Revolutions | C84: Philippines | D84: Cebu City | E84: The Gallery, Kasambagan, Cebu City | F84: Café / bar avec boutique | G84: Vinyl listening booths (from PHP350 incl. coffee), records sold on site, food and cocktails | O84: Rechercher sur Maps | Q84: Non vérifié | R84: =COUNTA(H84:M84) -> 0 | S84: Listening bar; hours reported 2-10PM. | T84: https://www.tiktok.com/discover/vinyl-cafe-cebu-menu | https://www.tiktok.com/discover/listening-cafe-vinyl
A85: 84 | B85: Unity Coffee & Vinyl | C85: Philippines | D85: Cebu City | E85: Don Jose Avila St., near CDUH, Cebu City | F85: Café / bar avec boutique | G85: Café with sizeable stock of vinyl records for sale | O85: Rechercher sur Maps | Q85: Non vérifié | R85: =COUNTA(H85:M85) -> 0 | S85: Newer breakfast/coffee spot; upstairs space for small events; hours reported 7/10AM-11PM. | T85: https://www.tiktok.com/discover/vinyl-cafe-cebu-menu
A86: 85 | B86: Dabawenyo CDs & Vinyl Records | C86: Philippines | D86: Davao City | F86: Vendeur réseaux sociaux | G86: Vinyl and CDs for collectors | J86: https://www.facebook.com/DabawenyoVinyl | Q86: Non vérifié | R86: =COUNTA(H86:M86) -> 1 | S86: Online music shop (Davao-based per name; no street address shown). | T86: https://www.facebook.com/DabawenyoVinyl/
A87: 86 | B87: Taurus Records and Vintage Collectibles | C87: Philippines | D87: Davao City | E87: 12 Taurus St., GSIS Heights, Matina, Davao City | F87: Boutique physique | G87: Vinyl records and vintage collectibles; vinyl DJ sets | J87: https://www.facebook.com/taurusrecordstore | L87: +63 922 849 7382 | O87: Rechercher sur Maps | Q87: Actif | R87: =COUNTA(H87:M87) -> 2 | S87: Bills itself as Davao City's first brick-and-mortar vinyl store; promoted vinyl DJ sets at a 2025 pop culture event. | T87: https://www.facebook.com/taurusrecordstore/
A88: 87 | B88: Anthology | C88: Philippines | D88: Iloilo City | E88: Block 1, Lot 13, Ledesco Village, Iloilo City | F88: En ligne (site web) | G88: New vinyl releases (pop, R&B, indie), e.g. SZA SOS Deluxe 4LP | H88: https://anthology-vinyl.com | I88: https://www.instagram.com/anthology.ilo | J88: https://www.facebook.com/anthology.ilo | M88: anthology.ilo@gmail.com | Q88: Actif | R88: =COUNTA(H88:M88) -> 4 | S88: Ships nationwide; in-stock list via link; ~6,900 IG followers; posts feature 2025 releases. | T88: https://www.facebook.com/anthology.ilo/ | https://www.instagram.com/anthology.ilo/
A89: 88 | B89: Prothrowbacks Records Vinyl LP's and 45's | C89: Philippines | D89: Mabalacat (Pampanga) | F89: Boutique physique | G89: Vintage collectible LPs, 45s and turntables | J89: https://www.facebook.com/vinylrecordsstore | O89: Rechercher sur Maps | Q89: Non vérifié | R89: =COUNTA(H89:M89) -> 1 | S89: FB page ~1,458 likes, with check-ins; located in Mabalacat, Pampanga (next to Angeles City). | T89: https://www.facebook.com/vinylrecordsstore/
A90: 89 | B90: Bebop Records | C90: Philippines | D90: Makati | E90: B1 Makati Central Square (Cinema Square), Chino Roces Ave. cor. Arnaiz Ave., Makati City | F90: Boutique physique | G90: Used/vintage vinyl; rare OPM classics, foreign metal and rock | O90: Rechercher sur Maps | Q90: Non vérifié | R90: =COUNTA(H90:M90) -> 0 | S90: Long-running Makati shop (mentioned in Discogs forum 10+ years ago); hours Mon-Sat 12:30-7PM per Bandwagon; Lifestyle Asia says no online channels. | T90: https://www.bandwagon.asia/articles/list-record-stores-in-manila-philippines-vinyl-shopping | https://lifestyleasia-onemega.com/arts-and-culture/7-places-to-buy-vinyl-records-in-manila/ | https://www.discogs.com/forum/thread/714753
A91: 90 | B91: Hodge Podge | C91: Philippines | D91: Makati | E91: San Agustin St., Legazpi Village, Makati City | F91: Café / bar avec boutique | G91: Record shop with vinyl listening space; coffee (free coffee with PHP250 purchase) | O91: Rechercher sur Maps | Q91: Non vérifié | R91: =COUNTA(H91:M91) -> 0 | S91: Seen on TikTok during soft opening (3-10PM hours at the time). | T91: https://www.tiktok.com/discover/vinyl-cafe-philippines | https://www.tiktok.com/discover/listening-cafe-vinyl
A92: 91 | B92: Mutilated Noise | C92: Philippines | D92: Makati | E92: Makati City | F92: Boutique physique | G92: Punk, hardcore; occasional secondhand original pressings of rare 80s/90s releases | O92: Rechercher sur Maps | Q92: Non vérifié | R92: =COUNTA(H92:M92) -> 0 | S92: Punk label that also runs a store; contact via Facebook messaging per Bandwagon. | T92: https://www.bandwagon.asia/articles/list-record-stores-in-manila-philippines-vinyl-shopping | https://news.abs-cbn.com/life/03/22/21/your-guide-to-hunting-for-vinyl-records-in-metro-manila
A93: 92 | B93: PlakaPlanet | C93: Philippines | D93: Makati | E93: Makati City (Wanderlog lists it as 'PlakaPlanet MCS', likely Makati Central Square) | F93: Boutique + en ligne | G93: New and vintage vinyl; strong Japanese section, OPM crates, bargain bin for beginners | I93: https://www.instagram.com/plakaplanet | J93: https://www.facebook.com/PlakaPlanetMakati | L93: 09332385993 | O93: Rechercher sur Maps | Q93: Actif | R93: =COUNTA(H93:M93) -> 3 | S93: Open daily 10:30AM-6:30PM; ships nationwide. Wanderlog listing (~late 2024) ranks it among Manila specialty shops. | T93: https://www.instagram.com/plakaplanet/ | https://www.facebook.com/PlakaPlanetMakati/ | https://wanderlog.com/list/geoCategory/756178/best-gift-and-souvenir-shops-speciality-and-artisan-stores-in-manila
A94: 93 | B94: Play Record Stop | C94: Philippines | D94: Makati | E94: 4963 Guerrero St., Makati City | F94: Boutique + en ligne | G94: Vinyl plus turntables and DJ mixers | O94: Rechercher sur Maps | Q94: Non vérifié | R94: =COUNTA(H94:M94) -> 0 | S94: Visits by appointment; pickup and delivery orders; weekdays 1-6PM. | T94: https://thesmartlocal.ph/?p=10840 | https://www.gmanetwork.com/entertainment/showbiznews/record-shops-for-vinyl-collectors-to-visit-in-metro-manila/70384/
A95: 94 | B95: Spindle Community Store (Spindle Hole) | C95: Philippines | D95: Makati | E95: Creekside Mall, Amorsolo St., Legazpi Village, Makati City | F95: Boutique physique | G95: Pre-owned and new vinyl, turntables, collectibles (Funko Pops) | O95: Rechercher sur Maps | Q95: Non vérifié | R95: =COUNTA(H95:M95) -> 0 | S95: Listed by Lifestyle Asia as Spindle Community Store; Crown Asia/ABS-CBN mention Spindle Hole (likely same business). | T95: https://lifestyleasia-onemega.com/arts-and-culture/7-places-to-buy-vinyl-records-in-manila/ | https://www.crownasia.com.ph/lifestyle-blog/turn-back-the-hands-of-time-best-places-to-buy-vinyl-records-in-the-philippines/ | https://news.abs-cbn.com/life/03/22/21/your-guide-to-hunting-for-vinyl-records-in-metro-manila
A96: 95 | B96: ThisisPop! Records | C96: Philippines | D96: Makati | E96: Legaspi Towers 100, Legaspi Village, Makati City | F96: Boutique physique | G96: Indie and obscure international acts, city pop, disco; Record Store Day releases | O96: Rechercher sur Maps | Q96: Non vérifié | R96: =COUNTA(H96:M96) -> 0 | S96: Record store linked to Toti Dalmacion (founder of Terno Recordings). Described on TikTok as a hidden record store in Legazpi Village. | T96: https://bandwagon.asia/articles/a-record-store-for-the-discerning-record-collector-thisispop-opens-today | https://news.abs-cbn.com/life/03/22/21/your-guide-to-hunting-for-vinyl-records-in-metro-manila | https://www.crownasia.com.ph/lifestyle-blog/turn-back-the-hands-of-time-best-places-to-buy-vinyl-records-in-the-philippines/ | https://www.tiktok.com/discover/vinyl-cafe-philippines
A97: 96 | B97: Backspacer Records | C97: Philippines | D97: Mandaluyong | E97: Flair Towers, Reliance cor. Pines St., Mandaluyong City; 2F D'Ace Plaza, Kapitolyo, Pasig City | F97: Boutique physique | G97: New vinyl; own limited-edition OPM pressings/collabs (Hey June!, Lola Amour, Kitchie Nadal); box sets; Record Store Day releases | O97: Rechercher sur Maps | Q97: Non vérifié | R97: =COUNTA(H97:M97) -> 0 | S97: Store and local label/distributor of OPM vinyl pressings; two shops (Mandaluyong and Kapitolyo, Pasig). Also acts as a label producing limited-edition OPM vinyl. | T97: https://www.bandwagon.asia/articles/list-record-stores-in-manila-philippines-vinyl-shopping | https://lifestyleasia-onemega.com/arts-and-culture/7-places-to-buy-vinyl-records-in-manila/ | https://news.abs-cbn.com/life/03/22/21/your-guide-to-hunting-for-vinyl-records-in-metro-manila
A98: 97 | B98: Satchmi | C98: Philippines | D98: Mandaluyong | E98: 4F Mega Fashion Hall, SM Megamall, Mandaluyong City (other branches incl. UP Town Center, Quezon City) | F98: Chaîne / grande enseigne | G98: New vinyl, own Motorino turntables, audio accessories; coffee and pastries; Record Store Day releases | O98: Rechercher sur Maps | Q98: Non vérifié | R98: =COUNTA(H98:M98) -> 0 | S98: Multi-branch vinyl/lifestyle retailer; reported as first PH store on official RSD roster (2018). | T98: https://www.crownasia.com.ph/lifestyle-blog/turn-back-the-hands-of-time-best-places-to-buy-vinyl-records-in-the-philippines/ | https://www.gmanetwork.com/entertainment/showbiznews/record-shops-for-vinyl-collectors-to-visit-in-metro-manila/70384/ | https://bandwagon.asia/articles/satchmi-record-store-day-2018
A99: 98 | B99: The Listening Room | C99: Philippines | D99: Mandaluyong | E99: Level 3, Building B, SM Megamall, Mandaluyong City | F99: Boutique physique | G99: New and secondhand vinyl (Beatles drawer), turntables and record-care supplies | O99: Rechercher sur Maps | Q99: Non vérifié | R99: =COUNTA(H99:M99) -> 0 | S99: Mall record shop; open daily 10AM-9PM per Lifestyle Asia. | T99: https://lifestyleasia-onemega.com/arts-and-culture/7-places-to-buy-vinyl-records-in-manila/ | https://news.abs-cbn.com/life/03/22/21/your-guide-to-hunting-for-vinyl-records-in-metro-manila
A100: 99 | B100: The Vinyl Cafe PH | C100: Philippines | D100: Mandaluyong | F100: Vendeur réseaux sociaux | G100: Vinyl records | J100: https://www.facebook.com/vinylcafePH | Q100: Non vérifié | R100: =COUNTA(H100:M100) -> 1 | S100: Online-only seller based in Mandaluyong. | T100: https://www.facebook.com/vinylcafePH/
...

Sheet Pokémon
A1: # | B1: Nom | C1: Pays | D1: Ville | E1: Adresse / zone | F1: Type | G1: Taille reseller | H1: Gros items (preuves) | I1: Priorité | J1: Spécialité (langues / produits) | K1: Site web | L1: Instagram | M1: Facebook | N1: TikTok | O1: Téléphone / WhatsApp | P1: Email | Q1: Marketplaces (Shopee, Lazada, Tokopedia…) | R1: Google Maps | S1: Vente en live | T1: Statut | U1: Nb canaux de contact | V1: Notes | W1: Sources
A2: 1 | B2: D Supreme Co., Ltd. (บริษัท ดี ซูพรีม จำกัด) | C2: Thaïlande | F2: Distributeur / grossiste | G2: Gros | H2: Distributes sealed Pokémon TCG product nationwide (booster boxes, premium collections) | I2: =IF(OR(G2="Gros",AND(H2<>"",S2="Oui")),"A",IF(OR(G2="Moyen",H2<>""),"B","C")) -> A | J2: Official sole distributor of Pokémon Trading Card Game in Thailand (per PR) | T2: Actif | U2: =COUNTA(K2:P2) -> 0 | V2: Brand Buffet PR (29 Apr 2026) calls it the sole Pokémon TCG distributor in Thailand; partnered with B2S (Central Retail) on the 'B2S Unseal Go Japan' campaign with The Pokémon Company's support. Contact details not found; HQ city not stated in source. | W2: https://www.brandbuffet.in.th/?p=28007
A3: 2 | B3: B2S | C3: Thaïlande | D3: Bangkok | E3: Nationwide B2S bookstore branches (Central Retail) | F3: Chaîne / grande enseigne | G3: Gros | H3: Premium collection products in Pokémon PLAY LAB | I3: =IF(OR(G3="Gros",AND(H3<>"",S3="Oui")),"A",IF(OR(G3="Moyen",H3<>""),"B","C")) -> A | J3: Pokémon TCG sets & accessories; Pokémon PLAY LAB space; tournaments | R3: Rechercher sur Maps | T3: Actif | U3: =COUNTA(K3:P3) -> 0 | V3: Runs B2S X Pokémon campaigns (B2S-exclusive promo card), the Pokémon PLAY LAB space at B2S CentralWorld, Pokémon PLAY LAB Fun Fest (6-12 Mar), and tournaments at Metro Mall venues (Feb-May 2026). Partner of sole distributor D Supreme. Separate entry for B2S Central Westgate (Nonthaburi). | W3: https://www.marketingoops.com/?p=290143 | https://www.marketingoops.com/?p=360729 | https://www.brandbuffet.in.th/?p=28007 | https://www.lemon8-app.com/@cattymeaw5/7359393930313646609?region=th
A4: 3 | B4: CARDWORLD BKK | C4: Thaïlande | D4: Bangkok | E4: Slow Combo Building, Soi Chula 50, Pathum Wan, Bangkok (near MRT Samyan Exit 2) | F4: Boutique + en ligne | G4: Gros | H4: PSA/BGS/SGC graded slabs; bills itself as Thailand's biggest card shop | I4: =IF(OR(G4="Gros",AND(H4<>"",S4="Oui")),"A",IF(OR(G4="Moyen",H4<>""),"B","C")) -> A | J4: Sports cards, Pokémon & general TCG; graded slabs (PSA/BGS/SGC); live auctions | L4: https://www.instagram.com/cardworld.bkk | R4: Rechercher sur Maps | S4: Oui | T4: Actif | U4: =COUNTA(K4:P4) -> 1 | V4: TCGTalk directory rating 5.0 (297 reviews); runs live auctions | W4: https://tcgtalk.com/guides/tcg-shops-thailand | https://tcgtalk.com/guides/thailand-pokemon-tradeshows-2026 | https://www.instagram.com/cardworld.bkk/ | https://www.lemon8-app.com/@white8z/7619997728135561749?region=th
A5: 4 | B5: Nx Gallery | C5: Thaïlande | D5: Bangkok | E5: Wang Thonglang, Bangkok (outlets near BTS Ari, BTS Phra Khanong, SC Plaza Taling Chan per TCGTalk) | F5: Café / bar avec boutique | G5: Gros | I5: =IF(OR(G5="Gros",AND(H5<>"",S5="Oui")),"A",IF(OR(G5="Moyen",H5<>""),"B","C")) -> A | J5: Pokémon TCG, MTG, One Piece, Union Arena, Gundam; card & board game café | R5: Rechercher sur Maps | T5: Actif | U5: =COUNTA(K5:P5) -> 0 | V5: LINE @nxgallery; multiple outlets (BTS Ari, BTS Phra Khanong, SC Plaza Taling Chan) plus Nx Gallery East in Rayong; TCGTalk 4.9 (256); closed Wednesdays | W5: https://tcgtalk.com/guides/tcg-shops-thailand | https://tcgtalk.com/guides/thailand-pokemon-tradeshows-2026
A6: 5 | B6: Pokémon Center Bangkok | C6: Thaïlande | D6: Bangkok | E6: CentralWorld, C604/2 Level 6, 4, 4/1-4/2, 4/4 Ratchadamri Rd, Pathum Wan, Bangkok 10330 | F6: Chaîne / grande enseigne | G6: Gros | H6: Official sealed TCG product (largest Pokémon Center outside Japan) | I6: =IF(OR(G6="Gros",AND(H6<>"",S6="Oui")),"A",IF(OR(G6="Moyen",H6<>""),"B","C")) -> A | J6: Official Pokémon store: TCG sealed product, plush, gachapon, merchandise | M6: https://www.facebook.com/PokemonThailand | R6: Rechercher sur Maps | T6: Non vérifié | U6: =COUNTA(K6:P6) -> 1 | V6: Official store announced May 2026 (largest Pokémon Center outside Japan); opening slated for late 2026 (Dec 2026 per TCGTalk), so it is not confirmed open as of 8 Oct 2026. The Facebook link is the official Pokémon Thailand page. | W6: https://bulbapedia.bulbagarden.net/wiki/Pok%C3%A9mon_Center_Bangkok | https://www.khaosodenglish.com/life/arts/2026/05/05/thailand-to-get-first-pokemon-center-at-centralworld-in-2026/ | https://sasom.co.th/articles/pok-mon-centre-bangkok-centralworld--thailand-s-first-store-and-the-largest-outside-japan-20260517 | https://www.elitefourum.com/t/pokemon-center-bangkok-to-open-in-2026/62263
A7: 6 | B7: Pika Trading | C7: Thaïlande | D7: Nakhon Ratchasima | E7: 3rd Floor, Terminal 21 Korat, Nakhon Ratchasima | F7: Distributeur / grossiste | G7: Gros | H7: Authorized distributor of sealed Thai-language Pokémon TCG product (per its Lazada listing) | I7: =IF(OR(G7="Gros",AND(H7<>"",S7="Oui")),"A",IF(OR(G7="Moyen",H7<>""),"B","C")) -> A | J7: Thai-language Pokémon TCG (sealed booster packs/boxes); distributor | M7: https://www.facebook.com/pikatrading.th | Q7: Lazada: Pika Trading | T7: Actif | U7: =COUNTA(K7:P7) -> 1 | V7: FB page describes it as a Pokémon card distributor; Lazada listing (SV11S Thai pack) names Pika Trading as authorized distributor of Thai Pokémon cards | W7: https://www.facebook.com/pikatrading.th/ | https://www.lazada.co.th/products/pokemon-booster-pack-sv11s-pokemon-tcg-thai-version-i5799251164.html
A8: 7 | B8: B2S Central Westgate (Pokémon zone) | C8: Thaïlande | D8: Nonthaburi | E8: B2S, Central Westgate, Bang Yai, Nonthaburi | F8: Chaîne / grande enseigne | G8: Gros | H8: Pokémon TCG boxes | I8: =IF(OR(G8="Gros",AND(H8<>"",S8="Oui")),"A",IF(OR(G8="Moyen",H8<>""),"B","C")) -> A | J8: Pokémon zone: TCG packs & boxes, plush, models, play tables | R8: Rechercher sur Maps | T8: Actif | U8: =COUNTA(K8:P8) -> 0 | V8: Branch of B2S chain (see B2S entry); Lemon8 post ~2024 | W8: https://www.lemon8-app.com/@pommeptr/7319060185409044994?region=us
A9: 8 | B9: Big Bear Cards and Hobby | C9: Thaïlande | D9: Bangkok | E9: Thanya Park, Srinagarindra Rd, Suan Luang, Bangkok | F9: Boutique physique | G9: Moyen | I9: =IF(OR(G9="Gros",AND(H9<>"",S9="Oui")),"A",IF(OR(G9="Moyen",H9<>""),"B","C")) -> B | J9: MTG (WPN Premium), Pokémon, Flesh and Blood, Altered, Transformers | R9: Rechercher sur Maps | T9: Actif | U9: =COUNTA(K9:P9) -> 0 | V9: TCGTalk 4.7 (18) | W9: https://tcgtalk.com/guides/tcg-shops-thailand
A10: 9 | B10: Nut Card | C10: Thaïlande | D10: Bangkok | E10: Room A513, 5th Floor, Mega Plaza Saphan Lek (Wang Burapha), Maha Chai Rd, Phra Nakhon, Bangkok | F10: Boutique physique | G10: Moyen | I10: =IF(OR(G10="Gros",AND(H10<>"",S10="Oui")),"A",IF(OR(G10="Moyen",H10<>""),"B","C")) -> B | J10: Pokémon TCG EN/JP/TH; Yu-Gi-Oh!, MTG, One Piece, Cookie Run, Braverse | L10: https://www.instagram.com/nutcard.th | M10: https://www.facebook.com/NutCardTCG | R10: Rechercher sur Maps | T10: Actif | U10: =COUNTA(K10:P10) -> 2 | V10: Hosts Pokémon TCG Town League events; FB page ~27.8k likes; TCGTalk 4.6 (229) | W10: https://tcgtalk.com/guides/tcg-shops-thailand | https://www.facebook.com/NutCardTCG/ | https://www.instagram.com/nutcard.th/
A11: 10 | B11: Pokémon card booth at Mixt Chatuchak (Zone A, Booth Y5) | C11: Thaïlande | D11: Bangkok | E11: 2nd Floor, Zone A, Booth Y5 (near escalator), Mixt Chatuchak, Bangkok (near BTS Mo Chit / MRT Chatuchak Park) | F11: Stand / marché | G11: Moyen | H11: Sells Pokémon boxes (ยกกล่อง) as well as single packs | I11: =IF(OR(G11="Gros",AND(H11<>"",S11="Oui")),"A",IF(OR(G11="Moyen",H11<>""),"B","C")) -> B | J11: Pokémon cards: sealed boxes and packs | R11: Rechercher sur Maps | T11: Actif | U11: =COUNTA(K11:P11) -> 0 | V11: Shop name not shown in result; Lemon8 post by @bearcarecard (~2024) may be the shop's own account | W11: https://www.lemon8-app.com/@bearcarecard/7409195085017498128?region=us
A12: 11 | B12: VG card shop | C12: Thaïlande | D12: Bangkok | E12: 3rd Floor, Room W3-08, The Old Siam Plaza, Pahurat, Bangkok | F12: Boutique + en ligne | G12: Moyen | I12: =IF(OR(G12="Gros",AND(H12<>"",S12="Oui")),"A",IF(OR(G12="Moyen",H12<>""),"B","C")) -> B | J12: Thai-language cards: Pokémon, Vanguard, Buddyfight, Battle Spirits; sleeves, deck boxes, playmats | K12: https://vgcardshop.com | M12: https://www.facebook.com/vgcardshop | O12: 090-279-7603 | R12: Rechercher sur Maps | T12: Actif | U12: =COUNTA(K12:P12) -> 3 | V12: Open Wed-Sun 11:00-17:30; posted singles for sale and a June 2026 event schedule; events posted Aug 2026 | W12: https://www.facebook.com/vgcardshop/
A13: 12 | B13: CaptainCards | C13: Thaïlande | D13: Pathum Thani | E13: 3rd Floor (West zone), Future Park Rangsit, Pathum Thani | F13: Boutique physique | G13: Moyen | I13: =IF(OR(G13="Gros",AND(H13<>"",S13="Oui")),"A",IF(OR(G13="Moyen",H13<>""),"B","C")) -> B | J13: Thai-language Pokémon TCG; TCG accessories | M13: https://www.facebook.com/captaincards | O13: 089-788-8741 | R13: Rechercher sur Maps | T13: Actif | U13: =COUNTA(K13:P13) -> 2 | W13: https://www.facebook.com/captaincards/
A14: 13 | B14: Nx Gallery East | C14: Thaïlande | D14: Rayong | E14: 3rd Floor, Central Plaza Rayong | F14: Café / bar avec boutique | G14: Moyen | I14: =IF(OR(G14="Gros",AND(H14<>"",S14="Oui")),"A",IF(OR(G14="Moyen",H14<>""),"B","C")) -> B | J14: Pokémon, MTG, One Piece, Union Arena, Gundam; TCG accessories | M14: https://www.facebook.com/nxgalleryeast | O14: 063-995-1716 | R14: Rechercher sur Maps | T14: Actif | U14: =COUNTA(K14:P14) -> 2 | V14: Card & board game café; branch of Nx Gallery | W14: https://www.facebook.com/nxgalleryeast/
A15: 14 | B15: CutieLand By POKO | C15: Thaïlande | F15: Vendeur réseaux sociaux | G15: Petit | I15: =IF(OR(G15="Gros",AND(H15<>"",S15="Oui")),"A",IF(OR(G15="Moyen",H15<>""),"B","C")) -> C | J15: Pre-orders of TCG & collectible cards: One Piece, Pokémon, Lorcana; toy store | M15: https://www.facebook.com/cutieland.bypoko | O15: 082-920-3223 | T15: Non vérifié | U15: =COUNTA(K15:P15) -> 2 | W15: https://www.facebook.com/cutieland.bypoko/
A16: 15 | B16: Thai Pkmn | C16: Thaïlande | F16: Vendeur réseaux sociaux | G16: Petit | I16: =IF(OR(G16="Gros",AND(H16<>"",S16="Oui")),"A",IF(OR(G16="Moyen",H16<>""),"B","C")) -> C | J16: Pokémon cards (Thai-based retailer), ships internationally | L16: https://www.instagram.com/thai_pkmn | T16: Non vérifié | U16: =COUNTA(K16:P16) -> 1 | V16: ~900 followers, 225 posts | W16: https://www.instagram.com/thai_pkmn/
A17: 16 | B17: Victory Card Shop | C17: Thaïlande | F17: Boutique physique | G17: Petit | I17: =IF(OR(G17="Gros",AND(H17<>"",S17="Oui")),"A",IF(OR(G17="Moyen",H17<>""),"B","C")) -> C | J17: Buddyfight, Vanguard, Battle Spirits (Pokémon not confirmed; surfaced in Pokémon booster-box search) | M17: https://www.facebook.com/VictoryCardShop | R17: Rechercher sur Maps | T17: Non vérifié | U17: =COUNTA(K17:P17) -> 1 | W17: https://www.facebook.com/VictoryCardShop/
A18: 17 | B18: สหพลการการ์ด (Sahaphon Card) | C18: Thaïlande | D18: Ayutthaya | F18: Boutique physique | G18: Petit | I18: =IF(OR(G18="Gros",AND(H18<>"",S18="Oui")),"A",IF(OR(G18="Moyen",H18<>""),"B","C")) -> C | J18: Pokémon, Battle of Talingchan, hololive, Bushiroad, Bandai products | M18: https://www.facebook.com/SKC3846 | R18: Rechercher sur Maps | T18: Non vérifié | U18: =COUNTA(K18:P18) -> 1 | V18: Claims 100% licensed products | W18: https://www.facebook.com/SKC3846/
A19: 18 | B19: Cardify | C19: Thaïlande | D19: Bangkok | E19: 2nd Floor, Soi Phutthamonthon Sai 1 (Buddhamonthon Lane 1), Phasi Charoen, Bangkok | F19: Boutique physique | G19: Petit | I19: =IF(OR(G19="Gros",AND(H19<>"",S19="Oui")),"A",IF(OR(G19="Moyen",H19<>""),"B","C")) -> C | J19: One Piece, Pokémon, Vanguard, Digimon, Dragon Ball, Ultraman | R19: Rechercher sur Maps | T19: Actif | U19: =COUNTA(K19:P19) -> 0 | V19: TCGTalk 5.0 (117); closed Mondays | W19: https://tcgtalk.com/guides/tcg-shops-thailand
A20: 19 | B20: GL Card Game Shop | C20: Thaïlande | D20: Bangkok | E20: Soi Sathorn 11 Yaek 5, opposite Assumption College Primary Section, Bangkok | F20: Boutique physique | G20: Petit | I20: =IF(OR(G20="Gros",AND(H20<>"",S20="Oui")),"A",IF(OR(G20="Moyen",H20<>""),"B","C")) -> C | J20: Card game shop (Pokémon offer to verify) | M20: https://www.facebook.com/glcardshop | R20: Rechercher sur Maps | T20: Non vérifié | U20: =COUNTA(K20:P20) -> 1 | W20: https://www.facebook.com/glcardshop/
A21: 20 | B21: Nova TCG Thailand | C21: Thaïlande | D21: Bangkok | E21: Ram Inthra 14 area, Bang Khen, Bangkok | F21: Boutique + en ligne | G21: Petit | I21: =IF(OR(G21="Gros",AND(H21<>"",S21="Oui")),"A",IF(OR(G21="Moyen",H21<>""),"B","C")) -> C | J21: Pokémon TCG with focus on Chinese-version (CN) Pokémon cards, accessories, toys, figures | L21: https://www.instagram.com/novatcg.thailand | R21: Rechercher sur Maps | T21: Actif | U21: =COUNTA(K21:P21) -> 1 | V21: TCGTalk 3.8 (26) | W21: https://tcgtalk.com/guides/tcg-shops-thailand | https://www.instagram.com/novatcg.thailand/
A22: 21 | B22: Pro Card | C22: Thaïlande | D22: Bangkok | E22: 5th Floor, MBK Center, Pathum Wan, Bangkok | F22: Boutique physique | G22: Petit | I22: =IF(OR(G22="Gros",AND(H22<>"",S22="Oui")),"A",IF(OR(G22="Moyen",H22<>""),"B","C")) -> C | J22: TCG card shop (Pokémon offer to verify) | M22: https://www.facebook.com/ProcardTCG | R22: Rechercher sur Maps | T22: Non vérifié | U22: =COUNTA(K22:P22) -> 1 | W22: https://www.facebook.com/ProcardTCG/
A23: 22 | B23: Sedai (เซได) | C23: Thaïlande | D23: Bangkok | E23: Sukhumvit 33, near BTS Phrom Phong, Bangkok | F23: Boutique physique | G23: Petit | I23: =IF(OR(G23="Gros",AND(H23<>"",S23="Oui")),"A",IF(OR(G23="Moyen",H23<>""),"B","C")) -> C | J23: Pokémon TCG plus art supplies | M23: https://www.facebook.com/Sedai4.5 | R23: Rechercher sur Maps | T23: Non vérifié | U23: =COUNTA(K23:P23) -> 1 | W23: https://www.facebook.com/Sedai4.5
A24: 23 | B24: Sit and Play | C24: Thaïlande | D24: Bangkok | F24: Boutique physique | G24: Petit | I24: =IF(OR(G24="Gros",AND(H24<>"",S24="Oui")),"A",IF(OR(G24="Moyen",H24<>""),"B","C")) -> C | J24: Pokémon TCG, MTG, Disney Lorcana, One Piece | M24: https://www.facebook.com/sitandplay.game | R24: Rechercher sur Maps | T24: Non vérifié | U24: =COUNTA(K24:P24) -> 1 | W24: https://www.facebook.com/sitandplay.game/
A25: 24 | B25: The Card Shop | C25: Thaïlande | D25: Bangkok | F25: Boutique + en ligne | G25: Petit | I25: =IF(OR(G25="Gros",AND(H25<>"",S25="Oui")),"A",IF(OR(G25="Moyen",H25<>""),"B","C")) -> C | J25: Card games & collectible cards: One Piece Card Game, Union Arena (Pokémon not confirmed) | M25: https://www.facebook.com/TheCardShopTH | O25: 086-056-8454 | R25: Rechercher sur Maps | T25: Non vérifié | U25: =COUNTA(K25:P25) -> 2 | W25: https://www.facebook.com/TheCardShopTH/
A26: 25 | B26: TMshop TCG Store | C26: Thaïlande | D26: Bangkok | E26: 40/11 Soi Sukhumvit 60/1, Bang Chak, Phra Khanong, Bangkok | F26: Boutique physique | G26: Petit | I26: =IF(OR(G26="Gros",AND(H26<>"",S26="Oui")),"A",IF(OR(G26="Moyen",H26<>""),"B","C")) -> C | J26: Collectible & TCG cards (Vanguard etc.) | M26: https://www.facebook.com/tmcardshop | R26: Rechercher sur Maps | T26: Non vérifié | U26: =COUNTA(K26:P26) -> 1 | W26: https://www.facebook.com/tmcardshop/
A27: 26 | B27: Wuwam Card Shop (วู่วามการ์ดชอป) | C27: Thaïlande | D27: Bangkok | E27: Room B236, 2nd Floor, Mega Plaza Saphan Lek, Bangkok | F27: Boutique physique | G27: Petit | I27: =IF(OR(G27="Gros",AND(H27<>"",S27="Oui")),"A",IF(OR(G27="Moyen",H27<>""),"B","C")) -> C | J27: Pokémon EN/JP; buy, sell & trade | M27: https://www.facebook.com/wuwamcardshop | R27: Rechercher sur Maps | T27: Actif | U27: =COUNTA(K27:P27) -> 1 | V27: Mentions Icon Siam / River City (events or branches - unclear) | W27: https://www.facebook.com/wuwamcardshop/
A28: 27 | B28: Tama Card | C28: Thaïlande | D28: Buriram | F28: Boutique physique | G28: Petit | I28: =IF(OR(G28="Gros",AND(H28<>"",S28="Oui")),"A",IF(OR(G28="Moyen",H28<>""),"B","C")) -> C | J28: Card shop (surfaced in Pokémon booster-box searches) | M28: https://www.facebook.com/TAMACardBuriram | R28: Rechercher sur Maps | T28: Non vérifié | U28: =COUNTA(K28:P28) -> 1 | W28: https://www.facebook.com/TAMACardBuriram/
A29: 28 | B29: P'N Card Games Shop | C29: Thaïlande | D29: Chiang Mai | E29: Soi 7, behind Chiang Mai University (near the Faculty of Engineering gate), Chiang Mai | F29: Boutique + en ligne | G29: Petit | I29: =IF(OR(G29="Gros",AND(H29<>"",S29="Oui")),"A",IF(OR(G29="Moyen",H29<>""),"B","C")) -> C | J29: Card game shop incl. Pokémon | L29: https://www.instagram.com/pncardgames | M29: https://www.facebook.com/PNCardGames | Q29: Shopee | R29: Rechercher sur Maps | T29: Actif | U29: =COUNTA(K29:P29) -> 2 | V29: FB page 'P'N Card Game' (~4,380 followers); held a card game tournament in Chiang Mai on 3-4 Oct 2026; sells via Facebook and Shopee (per IG hashtags) | W29: https://www.instagram.com/pncardgames/ | https://www.facebook.com/PNCardGames/
A30: 29 | B30: NK Card Hatyai | C30: Thaïlande | D30: Hat Yai | F30: Boutique physique | G30: Petit | I30: =IF(OR(G30="Gros",AND(H30<>"",S30="Oui")),"A",IF(OR(G30="Moyen",H30<>""),"B","C")) -> C | J30: Pokémon cards and other TCG | M30: https://www.facebook.com/nkcardhatyai | R30: Rechercher sur Maps | T30: Non vérifié | U30: =COUNTA(K30:P30) -> 1 | W30: https://www.facebook.com/nkcardhatyai/
A31: 30 | B31: PokéCore Hua-Hin TCG Shop.TH | C31: Thaïlande | D31: Hua Hin | E31: Near Central Hua Hin, opposite Wat Hua Hin, Prachuap Khiri Khan | F31: Boutique physique | G31: Petit | I31: =IF(OR(G31="Gros",AND(H31<>"",S31="Oui")),"A",IF(OR(G31="Moyen",H31<>""),"B","C")) -> C | J31: Pokémon TCG | R31: Rechercher sur Maps | T31: Actif | U31: =COUNTA(K31:P31) -> 0 | V31: TCGTalk 4.7 (14) | W31: https://tcgtalk.com/guides/tcg-shops-thailand
A32: 31 | B32: DonburiShop TCG KK | C32: Thaïlande | D32: Khon Kaen | F32: Boutique physique | G32: Petit | I32: =IF(OR(G32="Gros",AND(H32<>"",S32="Oui")),"A",IF(OR(G32="Moyen",H32<>""),"B","C")) -> C | J32: TCG shop (surfaced in Pokémon card-shop searches) | M32: https://www.facebook.com/DonburiShopkhonkaen | R32: Rechercher sur Maps | T32: Non vérifié | U32: =COUNTA(K32:P32) -> 1 | W32: https://www.facebook.com/DonburiShopkhonkaen
A33: 32 | B33: Iconic - Trading card game | C33: Thaïlande | D33: Khon Kaen | F33: Distributeur / grossiste | G33: Petit | I33: =IF(OR(G33="Gros",AND(H33<>"",S33="Oui")),"A",IF(OR(G33="Moyen",H33<>""),"B","C")) -> C | J33: Dealer for Vanguard, One Piece, Yu-Gi-Oh, Pokémon | M33: https://www.facebook.com/p/Iconic-Trading-card-game-61576280130672 | T33: Non vérifié | U33: =COUNTA(K33:P33) -> 1 | V33: Page describes itself as distributor/dealer of several card games | W33: https://www.facebook.com/p/Iconic-Trading-card-game-61576280130672/
A34: 33 | B34: Trick Room (Trick Room Card Shop) | C34: Thaïlande | D34: Nakhon Ratchasima | E34: 4th Floor, Central Korat, Nakhon Ratchasima | F34: Boutique physique | G34: Petit | I34: =IF(OR(G34="Gros",AND(H34<>"",S34="Oui")),"A",IF(OR(G34="Moyen",H34<>""),"B","C")) -> C | J34: Pokémon TCG, Battle of Talingchan, Beyblade X; play space / community hub | M34: https://www.facebook.com/TrickRoomCardShop | O34: +66 82 906 6501 | P34: trickroomcardgame@gmail.com | R34: Rechercher sur Maps | T34: Actif | U34: =COUNTA(K34:P34) -> 3 | V34: Has a Linktree; posted about Card Cult & Collectibles Convention 2026 | W34: https://www.facebook.com/TrickRoomCardShop/
A35: 34 | B35: D day card | C35: Thaïlande | D35: Pattaya | E35: 20/198-199 Moo 10, Soi Day Night, Pattaya Tai Rd (next to Tuk Com Pattaya South), Nong Prue, Bang Lamung, Chonburi | F35: Boutique physique | G35: Petit | I35: =IF(OR(G35="Gros",AND(H35<>"",S35="Oui")),"A",IF(OR(G35="Moyen",H35<>""),"B","C")) -> C | J35: Card game products & accessories (Pokémon offer to verify) | M35: https://www.facebook.com/p/D-day-card-100063579728865 | O35: +66 84 567 2356 | R35: Rechercher sur Maps | T35: Non vérifié | U35: =COUNTA(K35:P35) -> 2 | W35: https://www.facebook.com/p/D-day-card-100063579728865/
A36: 35 | B36: TCGIgnition | C36: Thaïlande | D36: Phuket | E36: 369/90 Yaowarat Rd (Soi Yaowarat 5), Talat Yai, Mueang Phuket | F36: Boutique physique | G36: Petit | I36: =IF(OR(G36="Gros",AND(H36<>"",S36="Oui")),"A",IF(OR(G36="Moyen",H36<>""),"B","C")) -> C | J36: Card game hub in Phuket (Pokémon offer not confirmed in snippet) | M36: https://www.facebook.com/p/TCGIgnition-100079263833060 | O36: +66 88 956 1424 | R36: Rechercher sur Maps | T36: Non vérifié | U36: =COUNTA(K36:P36) -> 2 | W36: https://www.facebook.com/p/TCGIgnition-100079263833060/
A37: 36 | B37: BLACK CARD TCG | C37: Thaïlande | D37: Ratchaburi | E37: Moo 3, Pak Raet, Ban Pong, Ratchaburi (event post also references Always One Plaza 5th Fl, Bangkok) | F37: Boutique physique | G37: Petit | I37: =IF(OR(G37="Gros",AND(H37<>"",S37="Oui")),"A",IF(OR(G37="Moyen",H37<>""),"B","C")) -> C | J37: Pokémon, One Piece and other card games | M37: https://www.facebook.com/p/BLACK-CARD-TCG-61583179858522 | O37: 097-146-5424 | R37: Rechercher sur Maps | T37: Actif | U37: =COUNTA(K37:P37) -> 2 | V37: Event dated 20 Sep 2026 | W37: https://www.facebook.com/p/BLACK-CARD-TCG-61583179858522/
A38: 37 | B38: BooM Card Games | C38: Thaïlande | D38: Surat Thani | E38: Sri Chaiya Rd, Talat, Mueang Surat Thani | F38: Boutique physique | G38: Petit | I38: =IF(OR(G38="Gros",AND(H38<>"",S38="Oui")),"A",IF(OR(G38="Moyen",H38<>""),"B","C")) -> C | J38: MTG, Vanguard, Yu-Gi-Oh, Battle of Talingchan, Lorcana; sleeves, deck boxes (Pokémon not listed in snippet) | M38: https://www.facebook.com/BooMCardGames | R38: Rechercher sur Maps | T38: Non vérifié | U38: =COUNTA(K38:P38) -> 1 | W38: https://www.facebook.com/BooMCardGames/
A39: 38 | B39: A&E บุ๊ค แอนด์ การ์ด (A&E Book and Card) | C39: Thaïlande | F39: Boutique physique | G39: Inconnu | I39: =IF(OR(G39="Gros",AND(H39<>"",S39="Oui")),"A",IF(OR(G39="Moyen",H39<>""),"B","C")) -> C | J39: Books & cards (surfaced in Pokémon booster-box searches) | M39: https://www.facebook.com/p/AE-%E0%B8%9A%E0%B8%B8%E0%B9%8A%E0%B8%84-%E0%B9%81%E0%B8%AD%E0%B8%99%E0%B8%94%E0%B9%8C-%E0%B8%81%E0%B8%B2%E0%B8%A3%E0%B9%8C%E0%B8%94-100083350831800 | R39: Rechercher sur Maps | T39: Non vérifié | U39: =COUNTA(K39:P39) -> 1 | W39: https://www.facebook.com/p/AE-%E0%B8%9A%E0%B8%B8%E0%B9%8A%E0%B8%84-%E0%B9%81%E0%B8%AD%E0%B8%99%E0%B8%94%E0%B9%8C-%E0%B8%81%E0%B8%B2%E0%B8%A3%E0%B9%8C%E0%B8%94-100083350831800/
A40: 39 | B40: ANNA SHOP | C40: Thaïlande | F40: Vendeur réseaux sociaux | G40: Inconnu | I40: =IF(OR(G40="Gros",AND(H40<>"",S40="Oui")),"A",IF(OR(G40="Moyen",H40<>""),"B","C")) -> C | J40: Surfaced in Thai search for Japanese Pokémon booster boxes; details not visible | M40: https://www.facebook.com/p/ANNA-SHOP-100063683825022 | T40: Non vérifié | U40: =COUNTA(K40:P40) -> 1 | W40: https://www.facebook.com/p/ANNA-SHOP-100063683825022/
A41: 40 | B41: Mikitoy Andcards | C41: Thaïlande | F41: Vendeur réseaux sociaux | G41: Inconnu | I41: =IF(OR(G41="Gros",AND(H41<>"",S41="Oui")),"A",IF(OR(G41="Moyen",H41<>""),"B","C")) -> C | J41: Toys and trading cards (surfaced in Pokémon card-shop searches) | M41: https://www.facebook.com/pongpan.nookeaw | T41: Non vérifié | U41: =COUNTA(K41:P41) -> 1 | W41: https://www.facebook.com/pongpan.nookeaw/
A42: 41 | B42: มอนอ Card Club (Mornor Card Club) | C42: Thaïlande | F42: Boutique physique | G42: Inconnu | I42: =IF(OR(G42="Gros",AND(H42<>"",S42="Oui")),"A",IF(OR(G42="Moyen",H42<>""),"B","C")) -> C | J42: Card club / card shop (surfaced in Pokémon card-shop searches) | M42: https://www.facebook.com/MornorCardClub | R42: Rechercher sur Maps | T42: Non vérifié | U42: =COUNTA(K42:P42) -> 1 | W42: https://www.facebook.com/MornorCardClub
A43: 42 | B43: ร้านสุภาพบุรุษ (SUPARBTOY) | C43: Thaïlande | F43: Vendeur réseaux sociaux | G43: Inconnu | I43: =IF(OR(G43="Gros",AND(H43<>"",S43="Oui")),"A",IF(OR(G43="Moyen",H43<>""),"B","C")) -> C | J43: Toy & card seller (surfaced in Pokémon booster-box searches) | M43: https://www.facebook.com/SUPARBTOY | T43: Non vérifié | U43: =COUNTA(K43:P43) -> 1 | W43: https://www.facebook.com/SUPARBTOY/
A44: 43 | B44: Cardmaster | C44: Thaïlande | D44: Bangkok | F44: Boutique physique | G44: Inconnu | I44: =IF(OR(G44="Gros",AND(H44<>"",S44="Oui")),"A",IF(OR(G44="Moyen",H44<>""),"B","C")) -> C | J44: Pokémon card shop recommended for Thai sets (per TCGTalk Thai guide) | R44: Rechercher sur Maps | T44: Non vérifié | U44: =COUNTA(K44:P44) -> 0 | V44: Named by TCGTalk's Thai Abyss Eye guide as a Bangkok place to buy | W44: https://tcgtalk.com/guides/thailand/abyss-eye-pull-rates-box-opening-guide
A45: 44 | B45: Gamebox | C45: Thaïlande | D45: Bangkok | F45: Boutique physique | G45: Inconnu | I45: =IF(OR(G45="Gros",AND(H45<>"",S45="Oui")),"A",IF(OR(G45="Moyen",H45<>""),"B","C")) -> C | J45: Card/game shop recommended for Pokémon Thai sets (per TCGTalk Thai guide) | R45: Rechercher sur Maps | T45: Non vérifié | U45: =COUNTA(K45:P45) -> 0 | V45: Named by TCGTalk's Thai Abyss Eye guide as a Bangkok place to buy | W45: https://tcgtalk.com/guides/thailand/abyss-eye-pull-rates-box-opening-guide
A46: 45 | B46: The Cardster (Bangkok International Card Show) | C46: Thaïlande | D46: Bangkok | E46: Shows at Samyan Mitrtown Hall 1-2, Bangkok (17-18 Oct 2026) and QSNCC (6-7 Mar 2027 edition) | F46: Stand / marché | G46: Inconnu | I46: =IF(OR(G46="Gros",AND(H46<>"",S46="Oui")),"A",IF(OR(G46="Moyen",H46<>""),"B","C")) -> C | J46: Card show organizer: sports cards & TCG vendors (incl. Pokémon); trade night after show | L46: https://www.instagram.com/bangkokcardshow | M46: https://www.facebook.com/bkkcardshow | R46: Rechercher sur Maps | T46: Actif | U46: =COUNTA(K46:P46) -> 2 | V46: Organizer of the Bangkok International Card Show, not a shop. Its vendor list is a good source of big resellers. IG handle of organizer: @thecardster.official | W46: https://tcgtalk.com/guides/thailand-pokemon-tradeshows-2026 | https://qsncc.com/en/whats-on/event-calendar/bangkok-international-card-show-2027/ | https://www.instagram.com/bangkokcardshow/
A47: 46 | B47: NIN TCG (NINTCG) | C47: Vietnam | D47: Hanoi | E47: Số 51 Ngõ Thịnh Hào 1, Đống Đa; 4-F5 Ngõ 171 Thái Hà, Đống Đa | F47: Boutique + en ligne | G47: Gros | I47: =IF(OR(G47="Gros",AND(H47<>"",S47="Oui")),"A",IF(OR(G47="Moyen",H47<>""),"B","C")) -> A | J47: Trading card games incl. Pokémon | K47: https://nintcg.com | R47: Rechercher sur Maps | T47: Actif | U47: =COUNTA(K47:P47) -> 1 | V47: Two Đống Đa locations; 5.0 (126 reviews); gathering point for northern collectors (TCGTalk). Size tier set to Large because it runs 2 branches. | W47: https://tcgtalk.com/guides/tcg-shops-vietnam | https://tcgtalk.com/blog/chaos-rising-pokemon-vietnam-guide-1777992511431
A48: 47 | B48: nShop | C48: Vietnam | D48: Ho Chi Minh City | E48: Branches: 239 Trần Quang Khải Q1; 66 Thành Thái Q10; Parc Mall 549 Tạ Quang Bửu Q8 (3F); AEON Mall Tân Phú Celadon (2F); Sunrise Plaza 27 Nguyễn Hữu Thọ Q7 | F48: Chaîne / grande enseigne | G48: Gros | I48: =IF(OR(G48="Gros",AND(H48<>"",S48="Oui")),"A",IF(OR(G48="Moyen",H48<>""),"B","C")) -> A | J48: Hobby/game chain (Nintendo Switch, PS5, Gundam) carrying Pokémon TCG; runs weekly community Pokémon TCG tournaments at AEON Malls | Hobby/game chain branch with Pokémon TCG product | K48: https://nshop.com.vn | R48: Rechercher sur Maps | T48: Actif | U48: =COUNTA(K48:P48) -> 1 | V48: One of Vietnam's largest hobby chains (TCGTalk); weekly community Pokémon TCG tournaments at AEON Mall Tân Phú, AEON Bình Tân, Parc Mall Q8; ~1,200 reviews (4.8). Hanoi branch at Lotte Mall West Lake listed separately. District 7 Sunrise Plaza branch 4.9 (121 reviews). | Hanoi branch of nShop chain, open daily 09:30–22:00 (TCGTalk). | W48: https://tcgtalk.com/guides/tcg-shops-vietnam | https://tcgtalk.com/guides/vietnam-pokemon-tradeshows-2026 | https://tcgtalk.com/blog/chaos-rising-pokemon-vietnam-guide-1777992511431
A49: 48 | B49: Zeni Card Central | C49: Vietnam | D49: Ho Chi Minh City | E49: Lầu 3, 772 Sư Vạn Hạnh, Quận 10 (second branch in Quận 4) | F49: Boutique physique | G49: Gros | I49: =IF(OR(G49="Gros",AND(H49<>"",S49="Oui")),"A",IF(OR(G49="Moyen",H49<>""),"B","C")) -> A | J49: Pokémon TCG singles-focused | R49: Rechercher sur Maps | T49: Actif | U49: =COUNTA(K49:P49) -> 0 | V49: TCGTalk: singles-leaning, 5.0 rating (283 reviews), opened a second branch in District 4. Size tier set to Large because it runs 2 branches (Q10 + Q4). | W49: https://tcgtalk.com/blog/chaos-rising-pokemon-vietnam-guide-1777992511431 | https://tcgtalk.com/guides/tcg-shops-vietnam
A50: 49 | B50: IPP Travel Retail (Duy Anh Trading JSC) - airport Pokémon TCG stores | C50: Vietnam | D50: Multiple | E50: Airport stores: Tan Son Nhat (HCMC), Noi Bai (Hanoi), Da Nang, Cam Ranh, Phu Quoc | F50: Chaîne / grande enseigne | G50: Gros | I50: =IF(OR(G50="Gros",AND(H50<>"",S50="Oui")),"A",IF(OR(G50="Moyen",H50<>""),"B","C")) -> A | J50: Pokémon TCG sold at airport stores (e.g., Kid Stars at Cam Ranh) | R50: Rechercher sur Maps | T50: Actif | U50: =COUNTA(K50:P50) -> 0 | V50: Moodie Davitt Report (2024): IPP Travel Retail launched Pokémon TCG at 5 Vietnamese airports; Pokémon cards among top sellers at Kid Stars Cam Ranh. Legal entity Duy Anh Trading JSC. | W50: https://moodiedavittreport.com/trinity-forum-host-ipp-travel-retail-brings-pokemon-trade-card-game-to-vietnamese-airports/ | https://moodiedavittreport.com/images-of-the-day-kid-stars-adds-colour-and-play-to-ipp-travel-retails-offer-at-cam-ranh-airport/ | https://aci-asiapac.aero/membership/wbp-capability-database/duy-anh-trading-joint-stock-company-ipp-travel-retail-1084104
A51: 50 | B51: BulbaShop | C51: Vietnam | D51: Hanoi | E51: 251 Trần Đăng Ninh, Dịch Vọng, Cầu Giấy | F51: Boutique + en ligne | G51: Moyen | I51: =IF(OR(G51="Gros",AND(H51<>"",S51="Oui")),"A",IF(OR(G51="Moyen",H51<>""),"B","C")) -> B | J51: Pokémon TCG specialist since 2017; genuine Pokémon product | K51: https://bulbashop.com | M51: https://www.facebook.com/bulbashop | O51: +84 977 179 496 | R51: Rechercher sur Maps | T51: Actif | U51: =COUNTA(K51:P51) -> 3 | V51: Hanoi's first Pokémon specialist (since 2017); 4.8 (129 reviews); Mon–Sat 09:00–17:00; FB ~4.5k followers. A cached FB snapshot showed the page as temporarily unavailable — confirm the page is live. | W51: https://tcgtalk.com/guides/tcg-shops-vietnam | https://www.facebook.com/bulbashop/ | https://tcgtalk.com/guides/vietnam-pokemon-tradeshows-2026
A52: 51 | B52: Mystic Crew TCG | C52: Vietnam | D52: Hanoi | E52: Tầng 4, Số 10 Trần Tử Bình, Nghĩa Tân, Cầu Giấy (TCGTalk guide also lists 106 Hoàng Quốc Việt) | F52: Boutique physique | G52: Moyen | I52: =IF(OR(G52="Gros",AND(H52<>"",S52="Oui")),"A",IF(OR(G52="Moyen",H52<>""),"B","C")) -> B | J52: TCG hub (buy/trade); Pokémon among games | M52: https://www.facebook.com/mysticcreww | O52: +84 92 463 29 29 | R52: Rechercher sur Maps | T52: Actif | U52: =COUNTA(K52:P52) -> 2 | V52: Named among Hanoi's key retailers by TCGTalk; 5.0 (205 reviews). | W52: https://www.facebook.com/mysticcreww/ | https://tcgtalk.com/guides/tcg-shops-vietnam | https://tcgtalk.com/blog/chaos-rising-pokemon-vietnam-guide-1777992511431
A53: 52 | B53: Hobby Center | C53: Vietnam | D53: Ho Chi Minh City | E53: 262/20 Lạc Long Quân, Quận 11 | F53: Boutique + en ligne | G53: Moyen | H53: Sealed product (TCGTalk calls its sealed/singles sourcing reliable); offers PSA grading submission service | I53: =IF(OR(G53="Gros",AND(H53<>"",S53="Oui")),"A",IF(OR(G53="Moyen",H53<>""),"B","C")) -> B | J53: Pokémon & One Piece TCG; Japanese TCG product; singles & sealed; PSA grading service | M53: https://www.facebook.com/hobbycenter.vn | R53: Rechercher sur Maps | T53: Actif | U53: =COUNTA(K53:P53) -> 1 | V53: TCGTalk rating 4.9 (291 reviews); FB page ~15k likes; hosts meetups/tournaments. | W53: https://tcgtalk.com/guides/tcg-shops-vietnam | https://tcgtalk.com/blog/chaos-rising-pokemon-vietnam-guide-1777992511431 | https://www.facebook.com/hobbycenter.vn/
A54: 53 | B54: MetroTCG | C54: Vietnam | D54: Ho Chi Minh City | F54: Boutique physique | G54: Moyen | H54: Imports Pokémon TCG product through the formal customs/tax channel (importer) | I54: =IF(OR(G54="Gros",AND(H54<>"",S54="Oui")),"A",IF(OR(G54="Moyen",H54<>""),"B","C")) -> B | J54: Pokémon TCG (imports through formal customs channel) | R54: Rechercher sur Maps | T54: Non vérifié | U54: =COUNTA(K54:P54) -> 0 | V54: LinkedIn post (#MetroTCG) claims it opened the first Pokémon TCG store in HCMC, engaged with the official distributor and is applying to become an official Pokémon Gym; linked to IPP Travel Retail. | W54: https://vn.linkedin.com/in/tonyphamvn
A55: 54 | B55: PokeHub TCG | C55: Vietnam | D55: Ho Chi Minh City | E55: 45 Nguyễn Thượng Hiền, Bình Thạnh (address flagged unverified by TCGTalk) | F55: Boutique physique | G55: Moyen | I55: =IF(OR(G55="Gros",AND(H55<>"",S55="Oui")),"A",IF(OR(G55="Moyen",H55<>""),"B","C")) -> B | J55: Pokémon TCG specialist, Japanese-focused (singles & sealed) | R55: Rechercher sur Maps | T55: Actif | U55: =COUNTA(K55:P55) -> 0 | V55: Listed by TCGTalk as Pokémon (Japanese) specialist, 5.0 rating (129 reviews), open until 22:00. Not to be confused with the PokeHub TCG Pocket app. | W55: https://tcgtalk.com/guides/tcg-shops-vietnam | https://tcgtalk.com/blog/chaos-rising-pokemon-vietnam-guide-1777992511431
A56: 55 | B56: PTCG Cần Thơ | C56: Vietnam | D56: Can Tho | E56: Phường An Khánh, Cần Thơ | F56: Vendeur réseaux sociaux | G56: Petit | I56: =IF(OR(G56="Gros",AND(H56<>"",S56="Oui")),"A",IF(OR(G56="Moyen",H56<>""),"B","C")) -> C | J56: Genuine Pokémon TCG booster packs; local community news & play tips | M56: https://www.facebook.com/PTCGCanTho | O56: +84 91 127 41 00 | T56: Non vérifié | U56: =COUNTA(K56:P56) -> 2 | V56: FB page lists delivery, pre-orders and in-store purchase; categorised as a personal blog, no reviews yet. | W56: https://www.facebook.com/PTCGCanTho/
A57: 56 | B57: Cá TCG - Đà Nẵng | C57: Vietnam | D57: Da Nang | F57: Vendeur réseaux sociaux | G57: Petit | H57: Sells Pokémon boxes | I57: =IF(OR(G57="Gros",AND(H57<>"",S57="Oui")),"A",IF(OR(G57="Moyen",H57<>""),"B","C")) -> B | J57: Pokémon TCG packs, boxes and singles (100% genuine claimed) | M57: https://www.facebook.com/people/C%C3%A1-TCG-%C4%90%C3%A0-N%E1%BA%B5ng/61570874096731 | O57: +84 97 866 33 51 | T57: Non vérifié | U57: =COUNTA(K57:P57) -> 2 | W57: https://www.facebook.com/people/C%C3%A1-TCG-%C4%90%C3%A0-N%E1%BA%B5ng/61570874096731/
A58: 57 | B58: Kawaii Kulture | C58: Vietnam | D58: Da Nang | E58: 21 Đầm Rong 1, Phường Thuận Phước, Hải Châu, Đà Nẵng | F58: Boutique + en ligne | G58: Petit | I58: =IF(OR(G58="Gros",AND(H58<>"",S58="Oui")),"A",IF(OR(G58="Moyen",H58<>""),"B","C")) -> C | J58: Genuine TCG: Pokémon, Yu-Gi-Oh!, MTG, One Piece, Digimon; toys | K58: https://kawaikulture.vn | M58: https://www.facebook.com/kawaiikulturedn | O58: +84 36 741 4859 | Q58: Shopee (shope.ee link on FB page) | R58: Rechercher sur Maps | T58: Non vérifié | U58: =COUNTA(K58:P58) -> 3 | V58: FB page 'Đồ chơi, thẻ bài chính hãng'. | W58: https://www.facebook.com/kawaiikulturedn/
A59: 58 | B59: PokeCorner | C59: Vietnam | D59: Ho Chi Minh City | E59: Hẻm 60 Lý Chính Thắng | F59: Boutique + en ligne | G59: Petit | I59: =IF(OR(G59="Gros",AND(H59<>"",S59="Oui")),"A",IF(OR(G59="Moyen",H59<>""),"B","C")) -> C | J59: Pokémon figures, merchandise and Pokémon TCG cards | K59: https://pokecorner.vn | M59: https://www.facebook.com/pokecornershop | R59: Rechercher sur Maps | T59: Non vérifié | U59: =COUNTA(K59:P59) -> 2 | V59: FB page: 'almost everything Pokémon' incl. TCG cards. | W59: https://www.facebook.com/pokecornershop/
A60: 59 | B60: Kichi TCG | C60: Vietnam | F60: Vendeur réseaux sociaux | G60: Inconnu | I60: =IF(OR(G60="Gros",AND(H60<>"",S60="Oui")),"A",IF(OR(G60="Moyen",H60<>""),"B","C")) -> C | J60: TCG store | M60: https://www.facebook.com/p/Kichi-TCG-61575859491723 | T60: Non vérifié | U60: =COUNTA(K60:P60) -> 1 | V60: Seen only as a Facebook page title in Vietnamese-language Pokémon TCG shop searches; location and Pokémon stock not confirmed. | W60: https://www.facebook.com/p/Kichi-TCG-61575859491723/
A61: 60 | B61: LangPokemonMTG (TikTok @pokemontcgviet) | C61: Vietnam | F61: Vendeur réseaux sociaux | G61: Inconnu | I61: =IF(OR(G61="Gros",AND(H61<>"",S61="Oui")),"A",IF(OR(G61="Moyen",H61<>""),"B","C")) -> C | J61: Vietnamese Pokémon TCG TikTok channel: box openings, Japanese Pokémon Center lottery (chiusen) guides, card shipping tips | N61: https://www.tiktok.com/@pokemontcgviet | T61: Non vérifié | U61: =COUNTA(K61:P61) -> 1 | V61: Runs TikTok Live box-opening sessions (#langpokemonmtg); whether it sells product was not confirmed — treat as a live-selling lead to verify. | W61: https://www.tiktok.com/@pokemontcgviet/video/7264878797223185665 | https://www.tiktok.com/@pokemontcgviet/video/7314918977514392839
A62: 61 | B62: Poke Poke - TCG Store | C62: Vietnam | F62: Vendeur réseaux sociaux | G62: Inconnu | I62: =IF(OR(G62="Gros",AND(H62<>"",S62="Oui")),"A",IF(OR(G62="Moyen",H62<>""),"B","C")) -> C | J62: TCG store (Pokémon implied by name) | M62: https://www.facebook.com/Pokepoketcg | T62: Non vérifié | U62: =COUNTA(K62:P62) -> 1 | V62: Seen only as a Facebook page title in Vietnamese-language Pokémon TCG shop searches; location and stock not confirmed. | W62: https://www.facebook.com/Pokepoketcg/
A63: 62 | B63: Pokioh | C63: Vietnam | F63: Vendeur réseaux sociaux | G63: Inconnu | H63: Korean Pokémon card boxes (box thẻ Pokemon bản Hàn) | I63: =IF(OR(G63="Gros",AND(H63<>"",S63="Oui")),"A",IF(OR(G63="Moyen",H63<>""),"B","C")) -> B | J63: Korean-language Pokémon TCG sealed boxes | M63: https://www.facebook.com/Pokioh.shop | T63: Non vérifié | U63: =COUNTA(K63:P63) -> 1 | V63: FB page @Pokioh.shop explicitly lists Korean-edition Pokémon card boxes; city not stated. | W63: https://www.facebook.com/Pokioh.shop/
A64: 63 | B64: Pokémon TCG Việt Nam (pokemontcg.vn) | C64: Vietnam | E64: 37 Hồng Hà (city not stated in source) | F64: Distributeur / grossiste | G64: Inconnu | I64: =IF(OR(G64="Gros",AND(H64<>"",S64="Oui")),"A",IF(OR(G64="Moyen",H64<>""),"B","C")) -> C | J64: Pokémon TCG — presents itself as the hub for Pokémon TCG players/fans in Vietnam | K64: https://pokemontcg.vn | M64: https://www.facebook.com/PokemonTCGVN | T64: Non vérifié | U64: =COUNTA(K64:P64) -> 2 | V64: FB page category is 'wholesale store' — possible importer/wholesaler; verify relationship to any official distribution. Hồng Hà street exists in both Hanoi and HCMC (Tân Bình), so city must be confirmed. TCGTalk separately cites a FB group 'Pokemon TCG Viet Nam – Official' as the main community channel. | W64: https://www.facebook.com/PokemonTCGVN/
A65: 64 | B65: Poke Store VN | C65: Vietnam | D65: Can Tho | F65: En ligne (site web) | G65: Inconnu | I65: =IF(OR(G65="Gros",AND(H65<>"",S65="Oui")),"A",IF(OR(G65="Moyen",H65<>""),"B","C")) -> C | J65: Pokémon TCG products, codes and items; pre-orders of new card sets | K65: https://pokestore.vn | M65: https://www.facebook.com/PokeStoreVN | O65: +84 94 806 65 14 | T65: Non vérifié | U65: =COUNTA(K65:P65) -> 3 | V65: FB category 'collectibles store' in Cần Thơ; description mentions Pokémon TCG codes/in-game items, while a post urges pre-ordering new cards — confirm physical card stock. | W65: https://www.facebook.com/PokeStoreVN
A66: 65 | B66: GG Coffee | C66: Vietnam | D66: Hanoi | E66: 15G Bùi Ngọc Dương, Hà Nội | F66: Café / bar avec boutique | G66: Inconnu | I66: =IF(OR(G66="Gros",AND(H66<>"",S66="Oui")),"A",IF(OR(G66="Moyen",H66<>""),"B","C")) -> C | J66: Trading cards (listed in TCG shop directory) | R66: Rechercher sur Maps | T66: Actif | U66: =COUNTA(K66:P66) -> 0 | V66: TCGTalk directory: open 10:00–20:00 daily, delivery available, 4.3 (328 reviews); Pokémon range not confirmed. | W66: https://tcgtalk.com/guides/tcg-shops-vietnam
A67: 66 | B67: Hero Game Hà Nội | C67: Vietnam | D67: Hanoi | E67: 20 P. Ngọc Khánh, Giảng Võ, Ba Đình | F67: Boutique physique | G67: Inconnu | I67: =IF(OR(G67="Gros",AND(H67<>"",S67="Oui")),"A",IF(OR(G67="Moyen",H67<>""),"B","C")) -> C | J67: Trading cards (multi-TCG) | O67: +84 937 666 822 | R67: Rechercher sur Maps | T67: Actif | U67: =COUNTA(K67:P67) -> 1 | V67: TCGTalk directory: open 09:00–20:00 daily. | W67: https://tcgtalk.com/guides/tcg-shops-vietnam
A68: 67 | B68: Cardlab | C68: Vietnam | D68: Ho Chi Minh City | E68: Lầu 2, 42 Tôn Thất Thiệp, Bến Nghé, Quận 1 | F68: Boutique physique | G68: Inconnu | I68: =IF(OR(G68="Gros",AND(H68<>"",S68="Oui")),"A",IF(OR(G68="Moyen",H68<>""),"B","C")) -> C | J68: Pokémon TCG retailer (trading cards) | M68: https://www.facebook.com/shoptcgsg | R68: Rechercher sur Maps | T68: Actif | U68: =COUNTA(K68:P68) -> 1 | V68: TCGTalk rating 4.7 (82 reviews); FB page describes it as a Pokémon trading card retailer. | W68: https://tcgtalk.com/guides/tcg-shops-vietnam | https://www.facebook.com/shoptcgsg/
A69: 68 | B69: GameStop Việt Nam | C69: Vietnam | D69: Ho Chi Minh City | E69: 1061 Phạm Văn Đồng, Phường Linh Tây, TP. Thủ Đức | F69: Boutique physique | G69: Inconnu | I69: =IF(OR(G69="Gros",AND(H69<>"",S69="Oui")),"A",IF(OR(G69="Moyen",H69<>""),"B","C")) -> C | J69: Pokémon card collecting (self-described) | R69: Rechercher sur Maps | T69: Non vérifié | U69: =COUNTA(K69:P69) -> 0 | V69: Only source is a self-published Tumblr (@gamestopvn) presenting it as a destination for Pokémon card collectors, with email on the gamestop.vn domain; not verified elsewhere. | W69: https://www.tumblr.com/gamestopvn
A70: 69 | B70: Geeky Mart LGS | C70: Vietnam | D70: Ho Chi Minh City | E70: Thảo Điền area, TP. Thủ Đức (exact address unconfirmed) | F70: Boutique physique | G70: Inconnu | I70: =IF(OR(G70="Gros",AND(H70<>"",S70="Oui")),"A",IF(OR(G70="Moyen",H70<>""),"B","C")) -> C | J70: Local game store / trading cards | R70: Rechercher sur Maps | T70: Actif | U70: =COUNTA(K70:P70) -> 0 | V70: TCGTalk directory: 4.9 (48 reviews). | W70: https://tcgtalk.com/guides/tcg-shops-vietnam
A71: 70 | B71: Herogame HCM | C71: Vietnam | D71: Ho Chi Minh City | E71: 200 Nguyễn Trọng Tuyển, Phường 8, Phú Nhuận | F71: Boutique physique | G71: Inconnu | I71: =IF(OR(G71="Gros",AND(H71<>"",S71="Oui")),"A",IF(OR(G71="Moyen",H71<>""),"B","C")) -> C | J71: Trading cards (multi-TCG) | R71: Rechercher sur Maps | T71: Actif | U71: =COUNTA(K71:P71) -> 0 | V71: TCGTalk directory: trading card store open 09:00–20:00 daily; Pokémon range not confirmed. | W71: https://tcgtalk.com/guides/tcg-shops-vietnam
A72: 71 | B72: HypecaT | C72: Vietnam | D72: Ho Chi Minh City | E72: 280/70/11 Bùi Hữu Nghĩa, Phường 2, Bình Thạnh | F72: Boutique physique | G72: Inconnu | I72: =IF(OR(G72="Gros",AND(H72<>"",S72="Oui")),"A",IF(OR(G72="Moyen",H72<>""),"B","C")) -> C | J72: Trading cards | R72: Rechercher sur Maps | T72: Actif | U72: =COUNTA(K72:P72) -> 0 | V72: TCGTalk directory: trading cards category, 4.9 (28 reviews). Pokémon range to be confirmed. | W72: https://tcgtalk.com/guides/tcg-shops-vietnam
A73: 72 | B73: M2 DUEL Store | C73: Vietnam | D73: Ho Chi Minh City | F73: Boutique + en ligne | G73: Inconnu | I73: =IF(OR(G73="Gros",AND(H73<>"",S73="Oui")),"A",IF(OR(G73="Moyen",H73<>""),"B","C")) -> C | J73: Yu-Gi-Oh! & Pokémon TCG, card accessories | K73: https://pro.m2duelstore.com | M73: https://www.facebook.com/M2duelstore | R73: Rechercher sur Maps | T73: Non vérifié | U73: =COUNTA(K73:P73) -> 2 | V73: Free home delivery advertised on FB page. | W73: https://www.facebook.com/M2duelstore/
A74: 73 | B74: SaiGon Collectibles | C74: Vietnam | D74: Ho Chi Minh City | E74: 105 Nguyễn Du, Quận 1 | F74: Boutique physique | G74: Inconnu | I74: =IF(OR(G74="Gros",AND(H74<>"",S74="Oui")),"A",IF(OR(G74="Moyen",H74<>""),"B","C")) -> C | J74: Pokémon & Yu-Gi-Oh! cards, collectibles | M74: https://www.facebook.com/SaigonCollectibles.vn | R74: Rechercher sur Maps | T74: Actif | U74: =COUNTA(K74:P74) -> 1 | V74: TCGTalk directory tags Pokémon and Yu-Gi-Oh. | W74: https://tcgtalk.com/guides/tcg-shops-vietnam | https://www.facebook.com/SaigonCollectibles.vn/
A75: 74 | B75: Saigon TCG (Saigon Trading Card Games) | C75: Vietnam | D75: Ho Chi Minh City | F75: Boutique physique | G75: Inconnu | I75: =IF(OR(G75="Gros",AND(H75<>"",S75="Oui")),"A",IF(OR(G75="Moyen",H75<>""),"B","C")) -> C | J75: Multi-TCG incl. Pokémon; associated with Vietnam TCG Fest announcements | R75: Rechercher sur Maps | T75: Actif | U75: =COUNTA(K75:P75) -> 0 | V75: TCGTalk names Saigon TCG as a main HCMC retailer; the 'Saigon Trading Card Games' fanpage posts Vietnam TCG Fest (December, HCMC) announcements — unclear whether shop or organiser. | W75: https://tcgtalk.com/blog/chaos-rising-pokemon-vietnam-guide-1777992511431 | https://tcgtalk.com/guides/vietnam-pokemon-tradeshows-2026
A76: 75 | B76: SBNV TCG Store | C76: Vietnam | D76: Ho Chi Minh City | F76: Boutique physique | G76: Inconnu | I76: =IF(OR(G76="Gros",AND(H76<>"",S76="Oui")),"A",IF(OR(G76="Moyen",H76<>""),"B","C")) -> C | J76: Pokémon TCG (tournaments/community events) | R76: Rechercher sur Maps | T76: Actif | U76: =COUNTA(K76:P76) -> 0 | V76: Named by TCGTalk as a key HCMC retailer; hosts monthly community tournaments; has a Facebook page. | W76: https://tcgtalk.com/guides/vietnam-pokemon-tradeshows-2026 | https://tcgtalk.com/blog/chaos-rising-pokemon-vietnam-guide-1777992511431
A77: 76 | B77: The Elite Card Game Store | C77: Vietnam | D77: Ho Chi Minh City | F77: Boutique physique | G77: Inconnu | I77: =IF(OR(G77="Gros",AND(H77<>"",S77="Oui")),"A",IF(OR(G77="Moyen",H77<>""),"B","C")) -> C | J77: Trading card games incl. Pokémon TCG | R77: Rechercher sur Maps | T77: Actif | U77: =COUNTA(K77:P77) -> 0 | V77: Named by TCGTalk as one of the key Pokémon TCG retailers in HCMC; address not found. | W77: https://tcgtalk.com/guides/vietnam-pokemon-tradeshows-2026 | https://tcgtalk.com/blog/chaos-rising-pokemon-vietnam-guide-1777992511431
A78: 77 | B78: Wano Games | C78: Vietnam | D78: Ho Chi Minh City | E78: Phú Nhuận | F78: Boutique physique | G78: Inconnu | I78: =IF(OR(G78="Gros",AND(H78<>"",S78="Oui")),"A",IF(OR(G78="Moyen",H78<>""),"B","C")) -> C | J78: Card & board game shop | R78: Rechercher sur Maps | T78: Actif | U78: =COUNTA(K78:P78) -> 0 | V78: TCGTalk directory: 4.9 (186 reviews); Pokémon range to be confirmed. | W78: https://tcgtalk.com/guides/tcg-shops-vietnam
A79: 78 | B79: Dannam Games & Hobbies | C79: Vietnam | D79: Nam Định | F79: Vendeur réseaux sociaux | G79: Inconnu | I79: =IF(OR(G79="Gros",AND(H79<>"",S79="Oui")),"A",IF(OR(G79="Moyen",H79<>""),"B","C")) -> C | J79: Online store for Pokémon cards / TCG | M79: https://www.facebook.com/TCGStoreVietNam | T79: Non vérifié | U79: =COUNTA(K79:P79) -> 1 | V79: FB page 'TCGStoreVietNam', located in Nam Định. | W79: https://www.facebook.com/TCGStoreVietNam/
A80: 79 | B80: Maxsoft (LazMall) | C80: Philippines | F80: Distributeur / grossiste | G80: Gros | H80: Pokémon TCG Mega Evolution Ascended Heroes Elite Trainer Box (PHP 4,399 on LazMall) | I80: =IF(OR(G80="Gros",AND(H80<>"",S80="Oui")),"A",IF(OR(G80="Moyen",H80<>""),"B","C")) -> A | J80: Official Pokémon merchandise/video-game distributor for SEA; sells EN Pokémon TCG sealed on LazMall | Q80: Lazada LazMall: Maxsoft | T80: Actif | U80: =COUNTA(K80:P80) -> 0 | V80: 2015 Bulbanews names Maxsoft authorized Pokémon distributor for Southeast Asia; 2019 GizGuide credits it with Nintendo distribution rights incl. PH and launching the Pokémon flagship store on Lazada PH. Its role in TCG distribution specifically is unconfirmed. | W80: https://www.lazada.com.ph/products/pokemon-tcg-mega-evolution-ascended-heroes-elite-trainer-box-i15389354988.html | https://www.gizguide.com/2019/12/pokemon-flagship-store-lazada-philippines.html | https://bulbanews.bulbagarden.net/wiki/Shiny_Rayquaza_to_be_distributed_by_Maxsoft_Online
A81: 80 | B81: Game One | C81: Philippines | D81: Metro Manila (multiple branches) | E81: Branches incl. SM North EDSA, Glorietta, SM Megamall | F81: Chaîne / grande enseigne | G81: Gros | H81: Official EN sealed incl. ETBs | I81: =IF(OR(G81="Gros",AND(H81<>"",S81="Oui")),"A",IF(OR(G81="Moyen",H81<>""),"B","C")) -> A | J81: Video games & official Pokémon TCG sets | R81: Rechercher sur Maps | T81: Actif | U81: =COUNTA(K81:P81) -> 0 | V81: Chain; named by TCGTalk as authorized channel; hosts weekly TCG sessions at Megamall. | W81: https://tcgtalk.com/guides/philippines/where-to-buy-pokemon-cards-philippines
A82: 81 | B82: Neutral Grounds | C82: Philippines | D82: Metro Manila (multiple branches) | F82: Chaîne / grande enseigne | G82: Gros | H82: Sealed boxes and singles (cited by TCGTalk) | I82: =IF(OR(G82="Gros",AND(H82<>"",S82="Oui")),"A",IF(OR(G82="Moyen",H82<>""),"B","C")) -> A | J82: Pokémon TCG, Magic: The Gathering, Yu-Gi-Oh!; singles and sealed | R82: Rechercher sur Maps | T82: Actif | U82: =COUNTA(K82:P82) -> 0 | V82: Long-running TCG chain with physical branches and an online store (TCGTalk 2026 guide). | W82: https://tcgtalk.com/guides/philippines/where-to-buy-pokemon-cards-philippines
A83: 82 | B83: Datablitz | C83: Philippines | D83: Nationwide (HQ Metro Manila) | E83: Mall branches (SM, Robinsons, Ayala, Trinoma) across Metro Manila; branches in Cebu, Iloilo, Davao | F83: Chaîne / grande enseigne | G83: Gros | H83: Official EN sealed (blisters, ETBs ~PHP2,600-3,200 for Ascended Heroes) | I83: =IF(OR(G83="Gros",AND(H83<>"",S83="Oui")),"A",IF(OR(G83="Moyen",H83<>""),"B","C")) -> A | J83: Official English Pokémon TCG sets; other TCGs (Union Arena etc.) | K83: https://ecommerce.datablitz.com.ph | R83: Rechercher sur Maps | T83: Actif | U83: =COUNTA(K83:P83) -> 1 | V83: Chain; named by TCGTalk as most accessible authorized channel for official EN sets; hosts tournaments. | W83: https://tcgtalk.com/guides/philippines/where-to-buy-pokemon-cards-philippines | https://ecommerce.datablitz.com.ph/products/pokemon-trading-card-game-enhanced-2-pack-blister
A84: 83 | B84: Toy Kingdom | C84: Philippines | D84: Nationwide (SM malls) | E84: SM mall branches nationwide (incl. SM Cebu, SM Davao) | F84: Chaîne / grande enseigne | G84: Gros | H84: Current-season EN sealed (narrower mix) | I84: =IF(OR(G84="Gros",AND(H84<>"",S84="Oui")),"A",IF(OR(G84="Moyen",H84<>""),"B","C")) -> A | J84: Official Pokémon items incl. current-season TCG sets and starter decks | K84: https://www.toykingdom.ph/collections/pokemon | R84: Rechercher sur Maps | T84: Actif | U84: =COUNTA(K84:P84) -> 1 | V84: Chain retailer (SM group); named as authorized Pokémon retail channel by TCGTalk. | W84: https://www.toykingdom.ph/collections/pokemon?page=1 | https://tcgtalk.com/guides/philippines/where-to-buy-pokemon-cards-philippines
A85: 84 | B85: Green Gate Hobbies | C85: Philippines | D85: Quezon City | E85: 857 Aurora Blvd. cor. St. Mary St., Cubao, Quezon City | F85: Boutique + en ligne | G85: Gros | H85: Sealed product and singles; collector-oriented stock; live auctions | I85: =IF(OR(G85="Gros",AND(H85<>"",S85="Oui")),"A",IF(OR(G85="Moyen",H85<>""),"B","C")) -> A | J85: Pokémon TCG sealed and singles; other TCGs | K85: https://shop.greengatehobbies.com | O85: +63 919 655 6270 | R85: Rechercher sur Maps | S85: Oui | T85: Actif | U85: =COUNTA(K85:P85) -> 2 | V85: Hosts official PTCG GYM Store events and live auctions; strong online store. Closed Mondays. | W85: https://tcgtalk.com/guides/tcg-shops-philippines | https://tcgtalk.com/guides/philippines/where-to-buy-pokemon-cards-philippines
A86: 85 | B86: Toys"R"Us Philippines (Pokémon Play Hub) | C86: Philippines | D86: Quezon City (Robinsons Galleria, Ortigas) | E86: Level 3, Robinsons Galleria, EDSA cor. Ortigas Ave. (Pokémon Play Hub); nationwide Toys R Us branches | F86: Chaîne / grande enseigne | G86: Gros | H86: Official Pokémon retail zone incl. exclusive items (TCG sealed availability to confirm) | I86: =IF(OR(G86="Gros",AND(H86<>"",S86="Oui")),"A",IF(OR(G86="Moyen",H86<>""),"B","C")) -> A | J86: Official Pokémon retail zone, TCG play area, beginner classes, sanctioned events | R86: Rechercher sur Maps | T86: Actif | U86: =COUNTA(K86:P86) -> 0 | V86: Chain retailer (Robinsons Retail). First official Pokémon Play Hub in PH, opened late 2025 with The Pokémon Company. | W86: https://www.robinsonsretailholdings.com.ph/2025/11/26/toysrus-pokemon-unveil-1st-pokemon-play-hub-in-ph/ | https://robinsonsmalls.com/pokemon-play-hub-robinsons-galleria
A87: 86 | B87: CO. the collectible store | C87: Philippines | D87: San Juan | E87: 3F Shoppesville, Greenhills Shopping Center, San Juan (also: Parkway area, SM City Fairview, Quezon City; GF Mitsukoshi Mall, Grand Central Park, BGC, Taguig) | F87: Boutique physique | G87: Gros | I87: =IF(OR(G87="Gros",AND(H87<>"",S87="Oui")),"A",IF(OR(G87="Moyen",H87<>""),"B","C")) -> A | J87: Collectibles store incl. Pokémon TCG | R87: Rechercher sur Maps | T87: Actif | U87: =COUNTA(K87:P87) -> 0 | V87: Multiple branches (Greenhills, SM Fairview, Mitsukoshi BGC) per TCGTalk guide. | W87: https://tcgtalk.com/blog/chaos-rising-pokemon-philippines-guide-1777992510344 | https://tcgtalk.com/guides/philippines/where-to-buy-pokemon-cards-philippines
A88: 87 | B88: Davao Magic Shop | C88: Philippines | D88: Davao City | E88: Cor. Lacson Torres St., Obrero, Davao City | F88: Boutique physique | G88: Moyen | I88: =IF(OR(G88="Gros",AND(H88<>"",S88="Oui")),"A",IF(OR(G88="Moyen",H88<>""),"B","C")) -> B | J88: TCG hobby store (MTG, Pokémon TCG) | M88: https://www.facebook.com/magicshopdavao | R88: Rechercher sur Maps | T88: Actif | U88: =COUNTA(K88:P88) -> 1 | V88: TCGTalk points to this store for Davao's official GYM events. | W88: https://tcgtalk.com/guides/tcg-shops-philippines | https://www.facebook.com/magicshopdavao/
A89: 88 | B89: Vault Card Shop | C89: Philippines | D89: Makati | E89: Circuit Lane, Carmona, Makati City, Metro Manila | F89: Boutique + en ligne | G89: Moyen | H89: Dedicated 'Sealed' product category (per FB page); recommended by TCGTalk for new-set release-day sealed stock | I89: =IF(OR(G89="Gros",AND(H89<>"",S89="Oui")),"A",IF(OR(G89="Moyen",H89<>""),"B","C")) -> B | J89: Pokémon, MTG, Yu-Gi-Oh!, One Piece and other TCGs; singles, sealed, accessories | K89: https://vaultcardshop.com | M89: https://www.facebook.com/VaultCardShop | O89: +63 962 281 6499 | R89: Rechercher sur Maps | T89: Actif | U89: =COUNTA(K89:P89) -> 3 | V89: Bills itself as a leading TCG hub in PH; TCGTalk rates it 4.9 (217 reviews) and calls it the strongest all-round pick in Metro Manila; open daily 10am-10pm. | W89: https://www.facebook.com/VaultCardShop/ | https://tcgtalk.com/blog/chaos-rising-pokemon-philippines-guide-1777992510344 | https://tcgtalk.com/guides/philippines/where-to-buy-pokemon-cards-philippines
A90: 89 | B90: Magus Games | C90: Philippines | D90: Mandaue City, Cebu | E90: Predico Building, Hernan Cortes St., Mandaue City, Cebu | F90: Boutique physique | G90: Moyen | I90: =IF(OR(G90="Gros",AND(H90<>"",S90="Oui")),"A",IF(OR(G90="Moyen",H90<>""),"B","C")) -> B | J90: Game store; Pokémon TCG and other TCGs | O90: +63 32 261 3586 | R90: Rechercher sur Maps | T90: Actif | U90: =COUNTA(K90:P90) -> 1 | V90: TCGTalk: Cebu store hosting regular official GYM events. Open daily 2-11pm. TCGTalk events page places the Hernan Cortes St. store in Cebu City. | W90: https://tcgtalk.com/guides/tcg-shops-philippines | https://tcgtalk.com/guides/philippines/where-to-buy-pokemon-cards-philippines
A91: 90 | B91: JapStore PH Cards & Hobbies | C91: Philippines | D91: Manila (Tondo) | E91: 363 Moriones St., Tondo, Manila | F91: Boutique + en ligne | G91: Moyen | I91: =IF(OR(G91="Gros",AND(H91<>"",S91="Oui")),"A",IF(OR(G91="Moyen",H91<>""),"B","C")) -> B | J91: Pokémon TCG and other TCGs; Japanese product | M91: https://www.facebook.com/p/JapStore-PH-Cards-Hobbies-100094538074584 | O91: +63 2 8743 7595 | R91: Rechercher sur Maps | T91: Actif | U91: =COUNTA(K91:P91) -> 2 | V91: Describes itself as a top TCG source in PH and an authorized Pokémon retailer supporting organized play; delivery and in-store pickup. | W91: https://www.facebook.com/p/JapStore-PH-Cards-Hobbies-100094538074584/
A92: 91 | B92: Gaming Library | C92: Philippines | D92: Metro Manila | F92: Boutique + en ligne | G92: Moyen | H92: Sealed boxes and singles (cited by TCGTalk) | I92: =IF(OR(G92="Gros",AND(H92<>"",S92="Oui")),"A",IF(OR(G92="Moyen",H92<>""),"B","C")) -> B | J92: TCG retailer; Pokémon sealed and singles | R92: Rechercher sur Maps | T92: Actif | U92: =COUNTA(K92:P92) -> 0 | W92: https://tcgtalk.com/guides/philippines/where-to-buy-pokemon-cards-philippines
A93: 92 | B93: Courtside | C93: Philippines | D93: Quezon City | E93: SM City North EDSA and Trinoma branches, Quezon City | F93: Boutique physique | G93: Moyen | I93: =IF(OR(G93="Gros",AND(H93<>"",S93="Oui")),"A",IF(OR(G93="Moyen",H93<>""),"B","C")) -> B | J93: Hobby shop (listed in TCG directory); Pokémon stock unconfirmed | R93: Rechercher sur Maps | T93: Actif | U93: =COUNTA(K93:P93) -> 0 | V93: Two branches; directory lists it only as a hobby shop - confirm Pokémon TCG offer. | W93: https://tcgtalk.com/guides/tcg-shops-philippines
A94: 93 | B94: Hobby Stadium | C94: Philippines | D94: Quezon City | E94: 3F, 84 Dona Hemady St. at E. Rodriguez St., New Manila, Quezon City | F94: Boutique physique | G94: Moyen | H94: Offers PSA, BGS and CGC grading services (per Instagram bio) | I94: =IF(OR(G94="Gros",AND(H94<>"",S94="Oui")),"A",IF(OR(G94="Moyen",H94<>""),"B","C")) -> B | J94: Pokémon TCG supplies, singles, booster packs; grading submissions (PSA/BGS/CGC) | L94: https://www.instagram.com/hobbystadium | O94: +63 919 091 7484 | R94: Rechercher sur Maps | T94: Actif | U94: =COUNTA(K94:P94) -> 2 | V94: Community-oriented; key official GYM event venue per TCGTalk. Hours Mon-Tue 2-11pm, Wed-Sun 11am-11pm. IG profile (@hobbystadium) matched by name; lists Pokémon and PSA/BGS/CGC grading. | W94: https://tcgtalk.com/blog/chaos-rising-pokemon-philippines-guide-1777992510344 | https://tcgtalk.com/guides/tcg-shops-philippines | https://www.instagram.com/hobbystadium/
A95: 94 | B95: RunIt Decks | C95: Philippines | D95: San Juan | E95: Upper level, Promenade Mall, Greenhills Shopping Center, San Juan City | F95: Boutique physique | G95: Moyen | H95: Recommended by TCGTalk for sealed product on new-set release days | I95: =IF(OR(G95="Gros",AND(H95<>"",S95="Oui")),"A",IF(OR(G95="Moyen",H95<>""),"B","C")) -> B | J95: Pokémon TCG and other TCGs; singles and sealed | R95: Rechercher sur Maps | T95: Actif | U95: =COUNTA(K95:P95) -> 0 | V95: 5.0 rating from 273 reviews (TCGTalk, May 2026). | W95: https://tcgtalk.com/blog/chaos-rising-pokemon-philippines-guide-1777992510344
A96: 95 | B96: Madcap Gaming Philippines | C96: Philippines | D96: San Pedro, Laguna | E96: San Pedro, Laguna | F96: Boutique physique | G96: Moyen | I96: =IF(OR(G96="Gros",AND(H96<>"",S96="Oui")),"A",IF(OR(G96="Moyen",H96<>""),"B","C")) -> B | J96: Game store; Pokémon TCG and other TCGs | O96: +63 995 200 7329 | R96: Rechercher sur Maps | T96: Actif | U96: =COUNTA(K96:P96) -> 1 | V96: TCGTalk: covers collectors south of Manila. Tue-Fri 2-11pm, weekends 11am-11pm. | W96: https://tcgtalk.com/blog/chaos-rising-pokemon-philippines-guide-1777992510344 | https://tcgtalk.com/guides/philippines/where-to-buy-pokemon-cards-philippines
A97: 96 | B97: NPC Café | C97: Philippines | D97: Calamba, Laguna | F97: Café / bar avec boutique | G97: Petit | I97: =IF(OR(G97="Gros",AND(H97<>"",S97="Oui")),"A",IF(OR(G97="Moyen",H97<>""),"B","C")) -> C | J97: Gaming café; TCG | O97: +63 917 572 7813 | R97: Rechercher sur Maps | T97: Actif | U97: =COUNTA(K97:P97) -> 1 | W97: https://tcgtalk.com/guides/tcg-shops-philippines
A98: 97 | B98: BOX 17 @ Unbox Cebu | C98: Philippines | D98: Cebu City | E98: Unbox Cebu, Ayala Central Bloc, Cebu IT Park, Cebu City | F98: Stand / marché | G98: Petit | I98: =IF(OR(G98="Gros",AND(H98<>"",S98="Oui")),"A",IF(OR(G98="Moyen",H98<>""),"B","C")) -> C | J98: Genuine Pokémon cards (consignment box/stall inside Unbox Cebu) | R98: Rechercher sur Maps | T98: Actif | U98: =COUNTA(K98:P98) -> 0 | V98: Recommended on TikTok for genuine Pokémon cards in Cebu. | W98: https://www.tiktok.com/discover/where-to-sell-pokemon-cards-philippines
A99: 98 | B99: Block 101 Hobbies | C99: Philippines | D99: Mandaluyong | E99: Ground Floor, Royal Plaza Commercial Center, Mandaluyong City | F99: Boutique physique | G99: Petit | I99: =IF(OR(G99="Gros",AND(H99<>"",S99="Oui")),"A",IF(OR(G99="Moyen",H99<>""),"B","C")) -> C | J99: TCG hobby shop & play space; Pokémon cards | R99: Rechercher sur Maps | T99: Actif | U99: =COUNTA(K99:P99) -> 0 | V99: TCGTalk: roomy, reasonably priced, sells drinks/snacks; good for collectors and players. Tue-Fri 2-10pm, Sat 2-7pm. | W99: https://tcgtalk.com/blog/chaos-rising-pokemon-philippines-guide-1777992510344
A100: 99 | B100: Ongkeco's Hobby Shop | C100: Philippines | D100: Manila (Malate) | E100: Cor. Taft Ave. & Estrada St., Malate, Manila | F100: Boutique physique | G100: Petit | I100: =IF(OR(G100="Gros",AND(H100<>"",S100="Oui")),"A",IF(OR(G100="Moyen",H100<>""),"B","C")) -> C | J100: Magic, NBA and Pokémon cards | M100: https://www.facebook.com/ongkeco.shop | O100: +63 917 536 3911 | R100: Rechercher sur Maps | T100: Actif | U100: =COUNTA(K100:P100) -> 2 | V100: 94% recommend (31 reviews) on FB. | W100: https://www.facebook.com/ongkeco.shop/ | https://tcgtalk.com/guides/tcg-shops-philippines
...
