Workbook

Sheet Résumé
A1: Lots musique – 250 lots entre RM45 et RM60 (Funko Pop : jusqu'à RM70)
A2: Prix et stock relevés le 20/10/2026 directement sur les boutiques (lien dans l'onglet Lots).
A4: Catégorie | B4: Objectif (%) | C4: Nb lots | D4: % réel | E4: Prix moyen (RM) | F4: Budget (RM) | G4: En réserve
A5: Vinyle | B5: 0.35 | C5: =COUNTIF(Lots!$B$2:$B$251,A5) -> 88 | D5: =IF($C$10=0,0,C5/$C$10) -> 0.352 | E5: =IFERROR(AVERAGEIF(Lots!$B$2:$B$251,A5,Lots!$D$2:$D$251),0) -> 52.363636 | F5: =SUMIF(Lots!$B$2:$B$251,A5,Lots!$D$2:$D$251) -> 4608 | G5: =COUNTIF(Réserve!$B$2:$B$277,A5) -> 151
A6: CD | B6: 0.25 | C6: =COUNTIF(Lots!$B$2:$B$251,A6) -> 62 | D6: =IF($C$10=0,0,C6/$C$10) -> 0.248 | E6: =IFERROR(AVERAGEIF(Lots!$B$2:$B$251,A6,Lots!$D$2:$D$251),0) -> 51.483871 | F6: =SUMIF(Lots!$B$2:$B$251,A6,Lots!$D$2:$D$251) -> 3192 | G6: =COUNTIF(Réserve!$B$2:$B$277,A6) -> 14
A7: Funko Pop | B7: reste | C7: =COUNTIF(Lots!$B$2:$B$251,A7) -> 75 | D7: =IF($C$10=0,0,C7/$C$10) -> 0.3 | E7: =IFERROR(AVERAGEIF(Lots!$B$2:$B$251,A7,Lots!$D$2:$D$251),0) -> 55.224133 | F7: =SUMIF(Lots!$B$2:$B$251,A7,Lots!$D$2:$D$251) -> 4141.81 | G7: =COUNTIF(Réserve!$B$2:$B$277,A7) -> 32
A8: Livre | B8: 0.05 | C8: =COUNTIF(Lots!$B$2:$B$251,A8) -> 13 | D8: =IF($C$10=0,0,C8/$C$10) -> 0.052 | E8: =IFERROR(AVERAGEIF(Lots!$B$2:$B$251,A8,Lots!$D$2:$D$251),0) -> 50.669231 | F8: =SUMIF(Lots!$B$2:$B$251,A8,Lots!$D$2:$D$251) -> 658.7 | G8: =COUNTIF(Réserve!$B$2:$B$277,A8) -> 17
A9: Autre | B9: reste | C9: =COUNTIF(Lots!$B$2:$B$251,A9) -> 12 | D9: =IF($C$10=0,0,C9/$C$10) -> 0.048 | E9: =IFERROR(AVERAGEIF(Lots!$B$2:$B$251,A9,Lots!$D$2:$D$251),0) -> 56.4 | F9: =SUMIF(Lots!$B$2:$B$251,A9,Lots!$D$2:$D$251) -> 676.8 | G9: =COUNTIF(Réserve!$B$2:$B$277,A9) -> 62
A10: Total | C10: =SUM(C5:C9) -> 250 | D10: =SUM(D5:D9) -> 1 | E10: =IFERROR(AVERAGE(Lots!$D$2:$D$251),0) -> 53.10924 | F10: =SUM(F5:F9) -> 13277.31 | G10: =SUM(G5:G9) -> 276
A11: Prix min / max | C11: =MIN(Lots!$D$2:$D$251) -> 45 | D11: =MAX(Lots!$D$2:$D$251) -> 70
A13: Méthode
A14: • Prix = prix article affiché sur la boutique, hors frais de port. Fourchette appliquée : RM45 ≤ prix ≤ RM60, sauf Funko Pop jusqu'à RM70.
A15: • Stock : disponibilité lue dans les données produit de la boutique (variante « disponible »), pas de précommande.
A16: • Boutiques malaisiennes en priorité ; les boutiques étrangères (ex. Singapour) indiquent la livraison et la conversion dans « Notes ».
A17: • CD : uniquement des albums cultes / classiques. Funko Pop : figurines de musiciens (Pop! Rocks, albums…).
A18: • Vinyles : quasi tous d'occasion (le neuf commence vers RM70 en Malaisie). Mudah.my = particuliers : confirmer avec le vendeur avant de payer.
A19: • Funko Pop : plafond relevé à RM70. Les Funko musique en stock en Malaisie passent en premier (Keepsake GSC, Legendary Toys, PXP, AxToysCentury) ; le reste vient de l'étranger, surtout Fugitive Toys (USA) : frais de port en plus, grouper la commande.
A20: • Onglet « Réserve » : produits valides en plus, pour remplacer un article épuisé.
A21: • Les stocks bougent vite : revérifier la disponibilité au moment de commander.

Sheet Lots
A1: N° | B1: Catégorie | C1: Produit | D1: Prix (RM) | E1: Lien | F1: Boutique | G1: Pays boutique | H1: Livraison Malaisie | I1: Stock vérifié | J1: Notes
A2: 1 | B2: Vinyle | C2: Altern 8 – Activ 8 (Come With Me) (12" single) | D2: 59 | E2: https://hardgraftrecords.com/electronic/altern-8-activ-8-come-with-me/ | F2: Hard Graft Records (Petaling Jaya) | G2: Malaysia | H2: Ships within Malaysia (also self-collect in PJ) | I2: WooCommerce Store API is_in_stock=true, '1 in stock' on 2026-10-20 | J2: Used/second-hand; media VG + / sleeve VG
A3: 2 | B3: Vinyle | C3: Altern 8 – Hypnotic St-8 (12" single) | D3: 59 | E3: https://hardgraftrecords.com/electronic/altern-8-hypnotic-st-8/ | F3: Hard Graft Records (Petaling Jaya) | G3: Malaysia | H3: Ships within Malaysia (also self-collect in PJ) | I3: WooCommerce Store API is_in_stock=true, '1 in stock' on 2026-10-20 | J3: Used/second-hand; media VG + / sleeve VG
A4: 3 | B4: Vinyle | C4: Barry Manilow – Barry (LP) | D4: 59 | E4: https://hardgraftrecords.com/pop/barry-manilow-barry/ | F4: Hard Graft Records (Petaling Jaya) | G4: Malaysia | H4: Ships within Malaysia (also self-collect in PJ) | I4: WooCommerce Store API is_in_stock=true, '1 in stock' on 2026-10-20 | J4: Used/second-hand; media VG ++ / sleeve VG +
A5: 4 | B5: Vinyle | C5: Bobby Brown – Rock Wit’Cha (“Love Beat” Mix) (12" single) | D5: 45 | E5: https://hardgraftrecords.com/rap-rnb/bobby-brown-rock-witcha-love-beat-mix/ | F5: Hard Graft Records (Petaling Jaya) | G5: Malaysia | H5: Ships within Malaysia (also self-collect in PJ) | I5: WooCommerce Store API is_in_stock=true, '1 in stock' on 2026-10-20 | J5: Used/second-hand; media VG + / sleeve VG
A6: 5 | B6: Vinyle | C6: Bomb The Bass Featuring Merlin / Lorraine – Megablast (Hip Hop On Precinct 13) (12" single) | D6: 45 | E6: https://hardgraftrecords.com/rap-rnb/bomb-the-bass-featuring-merlin-lorraine-megablast-hip-hop-on-precinct-13/ | F6: Hard Graft Records (Petaling Jaya) | G6: Malaysia | H6: Ships within Malaysia (also self-collect in PJ) | I6: WooCommerce Store API is_in_stock=true, '1 in stock' on 2026-10-20 | J6: Used/second-hand; media VG + / sleeve VG
A7: 6 | B7: Vinyle | C7: Bomb The Bass – Say A Little Prayer (12" single) | D7: 45 | E7: https://hardgraftrecords.com/funk-soul/bomb-the-bass-say-a-little-prayer/ | F7: Hard Graft Records (Petaling Jaya) | G7: Malaysia | H7: Ships within Malaysia (also self-collect in PJ) | I7: WooCommerce Store API is_in_stock=true, '1 in stock' on 2026-10-20 | J7: Used/second-hand; media VG + / sleeve VG
A8: 7 | B8: Vinyle | C8: Chicago, Chicago XIV LP (1980) | D8: 45 | E8: https://hardgraftrecords.com/pop/chicago-chicago-xiv-lp-1980/ | F8: Hard Graft Records (Petaling Jaya) | G8: Malaysia | H8: Ships within Malaysia (also self-collect in PJ) | I8: WooCommerce Store API is_in_stock=true, '1 in stock' on 2026-10-20 | J8: Used/second-hand; media VG+ / sleeve VG+
A9: 8 | B9: Vinyle | C9: Crystal Waters – Makin’ Happy (12" single) | D9: 49 | E9: https://hardgraftrecords.com/electronic/crystal-waters-makin-happy/ | F9: Hard Graft Records (Petaling Jaya) | G9: Malaysia | H9: Ships within Malaysia (also self-collect in PJ) | I9: WooCommerce Store API is_in_stock=true, '1 in stock' on 2026-10-20 | J9: Used/second-hand; media VG + / sleeve VG +
A10: 9 | B10: Vinyle | C10: En Vogue – Giving Him Something He Can Feel (12" single) | D10: 60 | E10: https://hardgraftrecords.com/funk-soul/en-vogue-giving-him-something-he-can-feel/ | F10: Hard Graft Records (Petaling Jaya) | G10: Malaysia | H10: Ships within Malaysia (also self-collect in PJ) | I10: WooCommerce Store API is_in_stock=true, '1 in stock' on 2026-10-20 | J10: Used/second-hand; media VG + / sleeve VG
A11: 10 | B11: Vinyle | C11: Guru Josh – Infinity (12" single) | D11: 45 | E11: https://hardgraftrecords.com/electronic/guru-josh-infinity/ | F11: Hard Graft Records (Petaling Jaya) | G11: Malaysia | H11: Ships within Malaysia (also self-collect in PJ) | I11: WooCommerce Store API is_in_stock=true, '1 in stock' on 2026-10-20 | J11: Used/second-hand
A12: 11 | B12: Vinyle | C12: Jackson Browne – Running On Empty (LP) | D12: 49 | E12: https://hardgraftrecords.com/rock/jackson-browne-running-on-empty/ | F12: Hard Graft Records (Petaling Jaya) | G12: Malaysia | H12: Ships within Malaysia (also self-collect in PJ) | I12: WooCommerce Store API is_in_stock=true, '1 in stock' on 2026-10-20 | J12: Used/second-hand; media VG + / sleeve VG
A13: 12 | B13: Vinyle | C13: Jon Anderson, 3 Ships LP (1985 US) | D13: 45 | E13: https://hardgraftrecords.com/rock/jon-anderson-3-ships-lp-1985-us/ | F13: Hard Graft Records (Petaling Jaya) | G13: Malaysia | H13: Ships within Malaysia (also self-collect in PJ) | I13: WooCommerce Store API is_in_stock=true, '1 in stock' on 2026-10-20 | J13: Used/second-hand; media VG++ / sleeve VG+
... A251: 250 | B251: Autre | C251: Pintrill Snoopy Blue Cap Records Pin | D251: 60 | E251: https://www.sweelee.com.my/products/pintrill-snoopy-blue-cap-records-pin | F251: Swee Lee Malaysia | G251: Malaysia | H251: Ships within Malaysia (Swee Lee MY online store) | I251: Shopify products.json variant available=true + tag stock_availability:in_stock, checked 2026-10-20 | J251: Pin's collector - Snoopy records-themed enamel pin (Peanuts licensed)

Sheet Réserve
A1: N° | B1: Catégorie | C1: Produit | D1: Prix (RM) | E1: Lien | F1: Boutique | G1: Pays boutique | H1: Livraison Malaisie | I1: Stock vérifié | J1: Notes
A2: 1 | B2: Vinyle | C2: Neil Diamond – Jonathan Livingston Seagull OST (LP, gatefold) | D2: 45 | E2: https://thryft.my/products/jonathan-livingston-seagull-original-motion-picture-sound-track | F2: Thryft (thryft.my – Malaysia storefront of Thryft Asia) | G2: Singapore | H2: Ships to Malaysia from SG: free delivery to West Malaysia for orders above RM80 (RM15 below RM80); East Malaysia quoted at checkout; 7-12 business days | I2: thryft.my/products/<handle>.js returned available=true and MYR price on 2026-10-20 (also listed in-stock in Shopify products.json) | J2: Preloved/used record (condition per listing photos). Price shown natively in MYR on thryft.my (SGD 11.90 on thryft.asia). One-off item (single copy).
A3: 2 | B3: Vinyle | C3: Neil Diamond – The Jazz Singer OST (LP, gatefold) | D3: 60 | E3: https://thryft.my/products/the-jazz-singer-original-songs-from-the-motion-picture-3 | F3: Thryft (thryft.my – Malaysia storefront of Thryft Asia) | G3: Singapore | H3: Ships to Malaysia from SG: free delivery to West Malaysia for orders above RM80 (RM15 below RM80); East Malaysia quoted at checkout; 7-12 business days | I3: thryft.my/products/<handle>.js returned available=true and MYR price on 2026-10-20 (also listed in-stock in Shopify products.json) | J3: Preloved/used record (condition per listing photos). Price shown natively in MYR on thryft.my (SGD 15.90 on thryft.asia). One-off item (single copy).
A4: 3 | B4: Vinyle | C4: Olivia Newton-John – Long Live Love (LP, Philippines press) | D4: 45 | E4: https://thryft.my/products/long-live-love | F4: Thryft (thryft.my – Malaysia storefront of Thryft Asia) | G4: Singapore | H4: Ships to Malaysia from SG: free delivery to West Malaysia for orders above RM80 (RM15 below RM80); East Malaysia quoted at checkout; 7-12 business days | I4: thryft.my/products/<handle>.js returned available=true and MYR price on 2026-10-20 (also listed in-stock in Shopify products.json) | J4: Preloved/used record (condition per listing photos). Price shown natively in MYR on thryft.my (SGD 11.90 on thryft.asia). One-off item (single copy).
A5: 4 | B5: Vinyle | C5: Paul Mauriat Orchestra – Paul Mauriat Orchestra (LP, 1975 SG/MY/HK release) | D5: 53 | E5: https://thryft.my/products/paul-mauriat-orchestra | F5: Thryft (thryft.my – Malaysia storefront of Thryft Asia) | G5: Singapore | H5: Ships to Malaysia from SG: free delivery to West Malaysia for orders above RM80 (RM15 below RM80); East Malaysia quoted at checkout; 7-12 business days | I5: thryft.my/products/<handle>.js returned available=true and MYR price on 2026-10-20 (also listed in-stock in Shopify products.json) | J5: Preloved/used record (condition per listing photos). Price shown natively in MYR on thryft.my (SGD 13.90 on thryft.asia). One-off item (single copy).
A6: 5 | B6: Vinyle | C6: Rick Springfield – Tao (LP) | D6: 60 | E6: https://thryft.my/products/tao-2 | F6: Thryft (thryft.my – Malaysia storefront of Thryft Asia) | G6: Singapore | H6: Ships to Malaysia from SG: free delivery to West Malaysia for orders above RM80 (RM15 below RM80); East Malaysia quoted at checkout; 7-12 business days | I6: thryft.my/products/<handle>.js returned available=true and MYR price on 2026-10-20 (also listed in-stock in Shopify products.json) | J6: Preloved/used record (condition per listing photos). Price shown natively in MYR on thryft.my (SGD 15.90 on thryft.asia). One-off item (single copy).
A7: 6 | B7: Vinyle | C7: Rod Stewart – Never A Dull Moment (LP, gatefold) | D7: 60 | E7: https://thryft.my/products/never-a-dull-moment | F7: Thryft (thryft.my – Malaysia storefront of Thryft Asia) | G7: Singapore | H7: Ships to Malaysia from SG: free delivery to West Malaysia for orders above RM80 (RM15 below RM80); East Malaysia quoted at checkout; 7-12 business days | I7: thryft.my/products/<handle>.js returned available=true and MYR price on 2026-10-20 (also listed in-stock in Shopify products.json) | J7: Preloved/used record (condition per listing photos). Price shown natively in MYR on thryft.my (SGD 15.90 on thryft.asia). One-off item (single copy).
A8: 7 | B8: Vinyle | C8: Roger Taylor (Queen) – Strange Frontier (LP) | D8: 49 | E8: https://thryft.my/products/strange-frontier | F8: Thryft (thryft.my – Malaysia storefront of Thryft Asia) | G8: Singapore | H8: Ships to Malaysia from SG: free delivery to West Malaysia for orders above RM80 (RM15 below RM80); East Malaysia quoted at checkout; 7-12 business days | I8: thryft.my/products/<handle>.js returned available=true and MYR price on 2026-10-20 (also listed in-stock in Shopify products.json) | J8: Preloved/used record (condition per listing photos). Price shown natively in MYR on thryft.my (SGD 12.90 on thryft.asia). One-off item (single copy).
A9: 8 | B9: Vinyle | C9: Sheena Easton – Do You (LP) | D9: 45 | E9: https://thryft.my/products/do-you | F9: Thryft (thryft.my – Malaysia storefront of Thryft Asia) | G9: Singapore | H9: Ships to Malaysia from SG: free delivery to West Malaysia for orders above RM80 (RM15 below RM80); East Malaysia quoted at checkout; 7-12 business days | I9: thryft.my/products/<handle>.js returned available=true and MYR price on 2026-10-20 (also listed in-stock in Shopify products.json) | J9: Preloved/used record (condition per listing photos). Price shown natively in MYR on thryft.my (SGD 11.90 on thryft.asia). One-off item (single copy).
A10: 9 | B10: Vinyle | C10: Sheena Easton – Madness, Money And Music (LP) | D10: 49 | E10: https://thryft.my/products/madness-money-and-music-1 | F10: Thryft (thryft.my – Malaysia storefront of Thryft Asia) | G10: Singapore | H10: Ships to Malaysia from SG: free delivery to West Malaysia for orders above RM80 (RM15 below RM80); East Malaysia quoted at checkout; 7-12 business days | I10: thryft.my/products/<handle>.js returned available=true and MYR price on 2026-10-20 (also listed in-stock in Shopify products.json) | J10: Preloved/used record (condition per listing photos). Price shown natively in MYR on thryft.my (SGD 12.90 on thryft.asia). One-off item (single copy).
A11: 10 | B11: Vinyle | C11: Sheena Easton – You Could Have Been With Me (LP) | D11: 56 | E11: https://thryft.my/products/you-could-have-been-with-me-1 | F11: Thryft (thryft.my – Malaysia storefront of Thryft Asia) | G11: Singapore | H11: Ships to Malaysia from SG: free delivery to West Malaysia for orders above RM80 (RM15 below RM80); East Malaysia quoted at checkout; 7-12 business days | I11: thryft.my/products/<handle>.js returned available=true and MYR price on 2026-10-20 (also listed in-stock in Shopify products.json) | J11: Preloved/used record (condition per listing photos). Price shown natively in MYR on thryft.my (SGD 14.90 on thryft.asia). One-off item (single copy).
A12: 11 | B12: Vinyle | C12: Sidney Bechet – Rocking! (LP) | D12: 56 | E12: https://thryft.my/products/rocking | F12: Thryft (thryft.my – Malaysia storefront of Thryft Asia) | G12: Singapore | H12: Ships to Malaysia from SG: free delivery to West Malaysia for orders above RM80 (RM15 below RM80); East Malaysia quoted at checkout; 7-12 business days | I12: thryft.my/products/<handle>.js returned available=true and MYR price on 2026-10-20 (also listed in-stock in Shopify products.json) | J12: Preloved/used record (condition per listing photos). Price shown natively in MYR on thryft.my (SGD 14.90 on thryft.asia). One-off item (single copy).
A13: 12 | B13: Vinyle | C13: Smokey Robinson – Smokey's World (LP) | D13: 53 | E13: https://thryft.my/products/smokeys-world | F13: Thryft (thryft.my – Malaysia storefront of Thryft Asia) | G13: Singapore | H13: Ships to Malaysia from SG: free delivery to West Malaysia for orders above RM80 (RM15 below RM80); East Malaysia quoted at checkout; 7-12 business days | I13: thryft.my/products/<handle>.js returned available=true and MYR price on 2026-10-20 (also listed in-stock in Shopify products.json) | J13: Preloved/used record (condition per listing photos). Price shown natively in MYR on thryft.my (SGD 13.90 on thryft.asia). One-off item (single copy).
... A277: 276 | B277: Autre | C277: Mitski "Be The Cowboy" Cassette | D277: 60 | E277: https://tandangstore.com/products/-mitski-be-the-cowboy-cassette-coming-soon--1 | F277: Tandang Records Store | G277: Malaysia | H277: Ships within Malaysia (KL record store, EasyStore checkout) | I277: Product page (MYR currency) available=true, category READY STOCK, inventory 1 - checked 2026-10-20 | J277: Cassette - Mitski album (handle mentions 'coming-soon' legacy but now tagged READY STOCK; only 1 unit)
